[{"code":"BN628DM-DP","name":"BNP PARIBAS ARBITRAGE MONTHLY DIVIDEND PAYOUT DIRECT PLAN","lump_available":"Y","sip_available":"Y","lump_min":5000.0,"lump_min_additional":1000.0,"lump_max":10000000000000.0,"lump_multiplier":1.0,"sip_min":500.0,"sip_max":1000000000.0,"sip_multiplier":1.0,"sip_dates":["1","2","3","4","5","6","7","8","9","10","11","12","13","14","15","16","17","18","19","20","21","22","23","24","25","26","27","28"],"purchase_amount_multiplier":"1","redemption_allowed":"Y","redemption_amount_multiple":0.001,"redemption_amount_minimum":1000.0,"redemption_quantity_multiple":0.001,"redemption_quantity_minimum":0.001,"category":"Hybrid","upsizecode_sip_dates":["1","2","3","4","5","6","7","8","9","10","11","12","13","14","15","16","17","18","19","20","21","22","23","24","25","26","27","28"],"sip_maximum_gap":60,"fund_house":"BNPPARIBAS_MF","ISIN":"INF251K01PF6","direct":"Y","switch_allowed":"Y","stp_flag":"Y","swp_flag":"Y","sips":[{"sip_frequency":"MONTHLY","sip_dates":["1","2","3","4","5","6","7","8","9","10","11","12","13","14","15","16","17","18","19","20","21","22","23","24","25","26","27","28"],"sip_minimum_gap":"0","sip_maximum_gap":"60"},{"sip_frequency":"QUARTERLY","sip_dates":["1","2","3","4","5","6","7","8","9","10","11","12","13","14","15","16","17","18","19","20","21","22","23","24","25","26","27","28"],"sip_minimum_gap":"0","sip_maximum_gap":"60"}],"instant":"N","nav":{"nav":10.069,"date":"2018-06-13"},"last_nav":{"nav":10.065,"date":"2018-06-12"},"volatility":2.04079,"returns":{"year_1":1.5837,"year_3":0.0,"year_5":0.0,"inception":1.9372,"date":"2018-06-13"},"detail_info":"http://www.bnpparibasmf.in/Downloads/index.aspx?Id=8","start_date":"2017-05-04","face_value":10.0,"fund_type":"Hybrid","fund_category":"Arbitrage Fund","plan":"DIVIDEND MONTHLY","expense_ratio":"0.44","fund_name":"BNP Paribas Mutual Fund","fund_manager":"Karthikraj Lakshmanan; Mayank Prakash","crisil_rating":"Moderately High","investment_objective":"To generate income and capital appreciation by investing in a combination of diversified portfolio of equity and equity related instruments; including use of equity derivatives strategies and arbitrage opportunities with exposure in debt and fixed income instruments.","portfolio_turnover":"12.38"},{"code":"BN628DM-DR","name":"BNP PARIBAS ARBITRAGE MONTHLY DIVIDEND REINVEST DIRECT PLAN","lump_available":"Y","sip_available":"Y","lump_min":5000.0,"lump_min_additional":1000.0,"lump_max":10000000000000.0,"lump_multiplier":1.0,"sip_min":500.0,"sip_max":1000000000.0,"sip_multiplier":1.0,"sip_dates":["1","2","3","4","5","6","7","8","9","10","11","12","13","14","15","16","17","18","19","20","21","22","23","24","25","26","27","28"],"purchase_amount_multiplier":"1","redemption_allowed":"Y","redemption_amount_multiple":0.001,"redemption_amount_minimum":1000.0,"redemption_quantity_multiple":0.001,"redemption_quantity_minimum":0.001,"category":"Hybrid","upsizecode_sip_dates":["1","2","3","4","5","6","7","8","9","10","11","12","13","14","15","16","17","18","19","20","21","22","23","24","25","26","27","28"],"sip_maximum_gap":60,"fund_house":"BNPPARIBAS_MF","ISIN":"INF251K01PE9","direct":"Y","switch_allowed":"Y","stp_flag":"Y","swp_flag":"Y","sips":[{"sip_frequency":"MONTHLY","sip_dates":["1","2","3","4","5","6","7","8","9","10","11","12","13","14","15","16","17","18","19","20","21","22","23","24","25","26","27","28"],"sip_minimum_gap":"0","sip_maximum_gap":"60"},{"sip_frequency":"QUARTERLY","sip_dates":["1","2","3","4","5","6","7","8","9","10","11","12","13","14","15","16","17","18","19","20","21","22","23","24","25","26","27","28"],"sip_minimum_gap":"0","sip_maximum_gap":"60"}],"instant":"N","nav":{"nav":10.069,"date":"2018-06-13"},"last_nav":{"nav":10.065,"date":"2018-06-12"},"volatility":2.04079,"returns":{"year_1":1.5837,"year_3":0.0,"year_5":0.0,"inception":1.9372,"date":"2018-06-13"},"detail_info":"http://www.bnpparibasmf.in/Downloads/index.aspx?Id=8","start_date":"2017-05-04","face_value":10.0,"fund_type":"Hybrid","fund_category":"Arbitrage Fund","plan":"DIVIDEND MONTHLY","expense_ratio":"0.44","fund_name":"BNP Paribas Mutual Fund","fund_manager":"Karthikraj Lakshmanan; Mayank Prakash","crisil_rating":"Moderately High","investment_objective":"To generate income and capital appreciation by investing in a combination of diversified portfolio of equity and equity related instruments; including use of equity derivatives strategies and arbitrage opportunities with exposure in debt and fixed income instruments.","portfolio_turnover":"12.38"},{"code":"BN628DQ-DP","name":"BNP PARIBAS ARBITRAGE QUARTERLY DIVIDEND PAYOUT DIRECT PLAN","lump_available":"Y","sip_available":"Y","lump_min":5000.0,"lump_min_additional":1000.0,"lump_max":10000000000000.0,"lump_multiplier":1.0,"sip_min":500.0,"sip_max":1000000000.0,"sip_multiplier":1.0,"sip_dates":["1","2","3","4","5","6","7","8","9","10","11","12","13","14","15","16","17","18","19","20","21","22","23","24","25","26","27","28"],"purchase_amount_multiplier":"1","redemption_allowed":"Y","redemption_amount_multiple":0.001,"redemption_amount_minimum":1000.0,"redemption_quantity_multiple":0.001,"redemption_quantity_minimum":0.001,"category":"Hybrid","upsizecode_sip_dates":["1","2","3","4","5","6","7","8","9","10","11","12","13","14","15","16","17","18","19","20","21","22","23","24","25","26","27","28"],"sip_maximum_gap":60,"fund_house":"BNPPARIBAS_MF","ISIN":"INF251K01PJ8","direct":"Y","switch_allowed":"Y","stp_flag":"Y","swp_flag":"Y","sips":[{"sip_frequency":"MONTHLY","sip_dates":["1","2","3","4","5","6","7","8","9","10","11","12","13","14","15","16","17","18","19","20","21","22","23","24","25","26","27","28"],"sip_minimum_gap":"0","sip_maximum_gap":"60"},{"sip_frequency":"QUARTERLY","sip_dates":["1","2","3","4","5","6","7","8","9","10","11","12","13","14","15","16","17","18","19","20","21","22","23","24","25","26","27","28"],"sip_minimum_gap":"0","sip_maximum_gap":"60"}],"instant":"N","nav":{"nav":10.18,"date":"2018-06-13"},"last_nav":{"nav":10.176,"date":"2018-06-12"},"volatility":3.00284,"returns":{"year_1":1.1024,"year_3":0.0,"year_5":0.0,"inception":1.6208,"date":"2018-06-13"},"detail_info":"http://www.bnpparibasmf.in/Downloads/index.aspx?Id=8","start_date":"2017-05-04","face_value":10.0,"fund_type":"Hybrid","fund_category":"Arbitrage Fund","plan":"DIVIDEND QUARTERLY","expense_ratio":"0.44","fund_name":"BNP Paribas Mutual Fund","fund_manager":"Karthikraj Lakshmanan; Mayank Prakash","crisil_rating":"Moderately High","investment_objective":"To generate income and capital appreciation by investing in a combination of diversified portfolio of equity and equity related instruments; including use of equity derivatives strategies and arbitrage opportunities with exposure in debt and fixed income instruments.","portfolio_turnover":"12.38"},{"code":"BN628DQ-DR","name":"BNP PARIBAS ARBITRAGE QUARTERLY DIVIDEND REINVEST DIRECT PLAN","lump_available":"Y","sip_available":"Y","lump_min":5000.0,"lump_min_additional":1000.0,"lump_max":10000000000000.0,"lump_multiplier":1.0,"sip_min":500.0,"sip_max":1000000000.0,"sip_multiplier":1.0,"sip_dates":["1","2","3","4","5","6","7","8","9","10","11","12","13","14","15","16","17","18","19","20","21","22","23","24","25","26","27","28"],"purchase_amount_multiplier":"1","redemption_allowed":"Y","redemption_amount_multiple":0.001,"redemption_amount_minimum":1000.0,"redemption_quantity_multiple":0.001,"redemption_quantity_minimum":0.001,"category":"Hybrid","upsizecode_sip_dates":["1","2","3","4","5","6","7","8","9","10","11","12","13","14","15","16","17","18","19","20","21","22","23","24","25","26","27","28"],"sip_maximum_gap":60,"fund_house":"BNPPARIBAS_MF","ISIN":"INF251K01PI0","direct":"Y","switch_allowed":"Y","stp_flag":"Y","swp_flag":"Y","sips":[{"sip_frequency":"QUARTERLY","sip_dates":["1","2","3","4","5","6","7","8","9","10","11","12","13","14","15","16","17","18","19","20","21","22","23","24","25","26","27","28"],"sip_minimum_gap":"0","sip_maximum_gap":"60"},{"sip_frequency":"MONTHLY","sip_dates":["1","2","3","4","5","6","7","8","9","10","11","12","13","14","15","16","17","18","19","20","21","22","23","24","25","26","27","28"],"sip_minimum_gap":"0","sip_maximum_gap":"60"}],"instant":"N","nav":{"nav":10.18,"date":"2018-06-13"},"last_nav":{"nav":10.176,"date":"2018-06-12"},"volatility":3.00284,"returns":{"year_1":1.1024,"year_3":0.0,"year_5":0.0,"inception":1.6208,"date":"2018-06-13"},"detail_info":"http://www.bnpparibasmf.in/Downloads/index.aspx?Id=8","start_date":"2017-05-04","face_value":10.0,"fund_type":"Hybrid","fund_category":"Arbitrage Fund","plan":"DIVIDEND QUARTERLY","expense_ratio":"0.44","fund_name":"BNP Paribas Mutual Fund","fund_manager":"Karthikraj Lakshmanan; Mayank Prakash","crisil_rating":"Moderately High","investment_objective":"To generate income and capital appreciation by investing in a combination of diversified portfolio of equity and equity related instruments; including use of equity derivatives strategies and arbitrage opportunities with exposure in debt and fixed income instruments.","portfolio_turnover":"12.38"},{"code":"BN630DD-DP","name":"BNP PARIBAS FOCUSED 25 EQUITY DIVIDEND PAYOUT DIRECT PLAN","lump_available":"Y","sip_available":"Y","lump_min":5000.0,"lump_min_additional":1000.0,"lump_max":10000000000000.0,"lump_multiplier":1.0,"sip_min":500.0,"sip_max":1000000000.0,"sip_multiplier":1.0,"sip_dates":["1","2","3","4","5","6","7","8","9","10","11","12","13","14","15","16","17","18","19","20","21","22","23","24","25","26","27","28"],"purchase_amount_multiplier":"1","redemption_allowed":"Y","redemption_amount_multiple":0.001,"redemption_amount_minimum":1000.0,"redemption_quantity_multiple":0.001,"redemption_quantity_minimum":0.001,"category":"Equity","upsizecode_sip_dates":["1","2","3","4","5","6","7","8","9","10","11","12","13","14","15","16","17","18","19","20","21","22","23","24","25","26","27","28"],"sip_maximum_gap":60,"fund_house":"BNPPARIBAS_MF","ISIN":"INF251K01PO8","direct":"Y","switch_allowed":"Y","stp_flag":"Y","swp_flag":"Y","sips":[{"sip_frequency":"MONTHLY","sip_dates":["1","2","3","4","5","6","7","8","9","10","11","12","13","14","15","16","17","18","19","20","21","22","23","24","25","26","27","28"],"sip_minimum_gap":"0","sip_maximum_gap":"60"},{"sip_frequency":"QUARTERLY","sip_dates":["1","2","3","4","5","6","7","8","9","10","11","12","13","14","15","16","17","18","19","20","21","22","23","24","25","26","27","28"],"sip_minimum_gap":"0","sip_maximum_gap":"60"}],"instant":"N","nav":{"nav":9.833,"date":"2018-06-13"},"last_nav":{"nav":9.867,"date":"2018-06-12"},"volatility":10.1984,"returns":{"year_1":0.0,"year_3":0.0,"year_5":0.0,"inception":-1.67,"date":"2018-06-13"},"detail_info":"http://www.bnpparibasmf.in/Downloads/index.aspx?Id=8","start_date":"2017-09-15","face_value":10.0,"fund_type":"Equity","fund_category":"Focused Fund","plan":"AS N WHEN","expense_ratio":"1.41","fund_name":"BNP Paribas Mutual Fund","fund_manager":"Karthikraj Lakshmanan; Abhijeet Dey","crisil_rating":"Moderately High","investment_objective":"to generate long-term capital growth by investing in a concentrated portfolio of equity \u0026 equity related instruments of up to 25 companies and the balance in debt securities \u0026 money market instruments","portfolio_turnover":"0.31"},{"code":"BN630DD-DR","name":"BNP PARIBAS FOCUSED 25 EQUITY DIVIDEND REINVEST DIRECT PLAN","lump_available":"Y","sip_available":"Y","lump_min":5000.0,"lump_min_additional":1000.0,"lump_max":10000000000000.0,"lump_multiplier":1.0,"sip_min":500.0,"sip_max":1000000000.0,"sip_multiplier":1.0,"sip_dates":["1","2","3","4","5","6","7","8","9","10","11","12","13","14","15","16","17","18","19","20","21","22","23","24","25","26","27","28"],"purchase_amount_multiplier":"1","redemption_allowed":"Y","redemption_amount_multiple":0.001,"redemption_amount_minimum":1000.0,"redemption_quantity_multiple":0.001,"redemption_quantity_minimum":0.001,"category":"Equity","upsizecode_sip_dates":["1","2","3","4","5","6","7","8","9","10","11","12","13","14","15","16","17","18","19","20","21","22","23","24","25","26","27","28"],"sip_maximum_gap":60,"fund_house":"BNPPARIBAS_MF","ISIN":"INF251K01PP5","direct":"Y","switch_allowed":"Y","stp_flag":"Y","swp_flag":"Y","sips":[{"sip_frequency":"MONTHLY","sip_dates":["1","2","3","4","5","6","7","8","9","10","11","12","13","14","15","16","17","18","19","20","21","22","23","24","25","26","27","28"],"sip_minimum_gap":"0","sip_maximum_gap":"60"},{"sip_frequency":"QUARTERLY","sip_dates":["1","2","3","4","5","6","7","8","9","10","11","12","13","14","15","16","17","18","19","20","21","22","23","24","25","26","27","28"],"sip_minimum_gap":"0","sip_maximum_gap":"60"}],"instant":"N","nav":{"nav":9.833,"date":"2018-06-13"},"last_nav":{"nav":9.867,"date":"2018-06-12"},"volatility":10.1984,"returns":{"year_1":0.0,"year_3":0.0,"year_5":0.0,"inception":-1.67,"date":"2018-06-13"},"detail_info":"http://www.bnpparibasmf.in/Downloads/index.aspx?Id=8","start_date":"2017-09-15","face_value":10.0,"fund_type":"Equity","fund_category":"Focused Fund","plan":"AS N WHEN","expense_ratio":"1.41","fund_name":"BNP Paribas Mutual Fund","fund_manager":"Karthikraj Lakshmanan; Abhijeet Dey","crisil_rating":"Moderately High","investment_objective":"to generate long-term capital growth by investing in a concentrated portfolio of equity \u0026 equity related instruments of up to 25 companies and the balance in debt securities \u0026 money market instruments","portfolio_turnover":"0.31"},{"code":"BN630DG-GR","name":"BNP PARIBAS FOCUSED 25 EQUITY GROWTH DIRECT PLAN","lump_available":"Y","sip_available":"Y","lump_min":5000.0,"lump_min_additional":1000.0,"lump_max":10000000000000.0,"lump_multiplier":1.0,"sip_min":500.0,"sip_max":1000000000.0,"sip_multiplier":1.0,"sip_dates":["1","2","3","4","5","6","7","8","9","10","11","12","13","14","15","16","17","18","19","20","21","22","23","24","25","26","27","28"],"purchase_amount_multiplier":"1","redemption_allowed":"Y","redemption_amount_multiple":0.001,"redemption_amount_minimum":1000.0,"redemption_quantity_multiple":0.001,"redemption_quantity_minimum":0.001,"category":"Equity","upsizecode_sip_dates":["1","2","3","4","5","6","7","8","9","10","11","12","13","14","15","16","17","18","19","20","21","22","23","24","25","26","27","28"],"sip_maximum_gap":60,"fund_house":"BNPPARIBAS_MF","ISIN":"INF251K01PN0","direct":"Y","switch_allowed":"Y","stp_flag":"Y","swp_flag":"Y","sips":[{"sip_frequency":"MONTHLY","sip_dates":["1","2","3","4","5","6","7","8","9","10","11","12","13","14","15","16","17","18","19","20","21","22","23","24","25","26","27","28"],"sip_minimum_gap":"0","sip_maximum_gap":"60"},{"sip_frequency":"QUARTERLY","sip_dates":["1","2","3","4","5","6","7","8","9","10","11","12","13","14","15","16","17","18","19","20","21","22","23","24","25","26","27","28"],"sip_minimum_gap":"0","sip_maximum_gap":"60"}],"instant":"N","nav":{"nav":9.838,"date":"2018-06-13"},"last_nav":{"nav":9.871,"date":"2018-06-12"},"volatility":10.2018,"returns":{"year_1":0.0,"year_3":0.0,"year_5":0.0,"inception":-1.62,"date":"2018-06-13"},"detail_info":"http://www.bnpparibasmf.in/Downloads/index.aspx?Id=8","start_date":"2017-09-15","face_value":10.0,"fund_type":"Equity","fund_category":"Focused Fund","plan":"GROWTH","expense_ratio":"1.41","fund_name":"BNP Paribas Mutual Fund","fund_manager":"Karthikraj Lakshmanan; Abhijeet Dey","crisil_rating":"Moderately High","investment_objective":"to generate long-term capital growth by investing in a concentrated portfolio of equity \u0026 equity related instruments of up to 25 companies and the balance in debt securities \u0026 money market instruments","portfolio_turnover":"0.31"},{"code":"TAFW1Z-DR","name":"TATA TREASURY ADVANTAGE WEEKLY DIVIDEND REINVEST DIRECT PLAN","lump_available":"Y","sip_available":"Y","lump_min":5000.0,"lump_min_additional":1000.0,"lump_max":10000000000000.0,"lump_multiplier":1.0,"sip_min":500.0,"sip_max":1000000000.0,"sip_multiplier":1.0,"sip_dates":["1","2","3","4","5","6","7","8","9","10","11","12","13","14","15","16","17","18","19","20","21","22","23","24","25","26","27","28","29","30"],"purchase_amount_multiplier":"1","redemption_allowed":"Y","redemption_amount_multiple":1.0,"redemption_amount_minimum":1000.0,"redemption_quantity_multiple":0.001,"redemption_quantity_minimum":0.001,"category":"Debt","upsizecode_sip_dates":["1","2","3","4","5","6","7","8","9","10","11","12","13","14","15","16","17","18","19","20","21","22","23","24","25","26","27","28","29","30"],"sip_maximum_gap":90,"fund_house":"TATAMutualFund_MF","ISIN":"INF277K010C8","direct":"Y","switch_allowed":"Y","stp_flag":"Y","swp_flag":"Y","sips":[{"sip_frequency":"QUARTERLY","sip_dates":["1","2","3","4","5","6","7","8","9","10","11","12","13","14","15","16","17","18","19","20","21","22","23","24","25","26","27","28","29","30"],"sip_minimum_gap":"0","sip_maximum_gap":"90"},{"sip_frequency":"MONTHLY","sip_dates":["1","2","3","4","5","6","7","8","9","10","11","12","13","14","15","16","17","18","19","20","21","22","23","24","25","26","27","28","29","30"],"sip_minimum_gap":"0","sip_maximum_gap":"90"}],"instant":"N","nav":{"nav":1008.45,"date":"2018-06-13"},"last_nav":{"nav":1008.07,"date":"2018-06-12"},"volatility":1.05171,"returns":{"year_1":4.8385,"year_3":5.5632,"year_5":6.1679,"inception":6.3479,"date":"2018-06-13"},"detail_info":"http://www.tatamutualfund.com/downloads/scheme-information-document","start_date":"2013-01-01","face_value":1000.0,"fund_type":"Debt","fund_category":"Low Duration Fund","plan":"DIVIDEND WEEKLY","expense_ratio":"0.15","fund_name":"Tata Mutual Fund","fund_manager":"Akhil Mittal","crisil_rating":"Moderately Low","investment_objective":"To generate stable returns with a low interest rate risk strategy by creating a portfolio that is predominantly invested in good quality floating rate debt instruments; money market instruments and fixed rate debt instruments which can also be swapped for floating rate returns.","portfolio_turnover":""},{"code":"TAIPHDZ-DP","name":"TATA INDIA PHARMA AND HEATHCARE DIVIDEND PAYOUT DIRECT PLAN","lump_available":"Y","sip_available":"Y","lump_min":5000.0,"lump_min_additional":1000.0,"lump_max":10000000000000.0,"lump_multiplier":1.0,"sip_min":500.0,"sip_max":1000000000.0,"sip_multiplier":1.0,"sip_dates":["1","2","3","4","5","6","7","8","9","10","11","12","13","14","15","16","17","18","19","20","21","22","23","24","25","26","27","28","29","30"],"purchase_amount_multiplier":"1","redemption_allowed":"Y","redemption_amount_multiple":1.0,"redemption_amount_minimum":500.0,"redemption_quantity_multiple":0.001,"redemption_quantity_minimum":0.001,"category":"Equity","upsizecode_sip_dates":["1","2","3","4","5","6","7","8","9","10","11","12","13","14","15","16","17","18","19","20","21","22","23","24","25","26","27","28","29","30"],"sip_maximum_gap":90,"fund_house":"TATAMutualFund_MF","ISIN":"INF277K011B8","direct":"Y","switch_allowed":"Y","stp_flag":"Y","swp_flag":"Y","sips":[{"sip_frequency":"QUARTERLY","sip_dates":["1","2","3","4","5","6","7","8","9","10","11","12","13","14","15","16","17","18","19","20","21","22","23","24","25","26","27","28","29","30"],"sip_minimum_gap":"0","sip_maximum_gap":"90"},{"sip_frequency":"MONTHLY","sip_dates":["1","2","3","4","5","6","7","8","9","10","11","12","13","14","15","16","17","18","19","20","21","22","23","24","25","26","27","28","29","30"],"sip_minimum_gap":"0","sip_maximum_gap":"90"}],"instant":"N","nav":{"nav":8.8139,"date":"2018-06-13"},"last_nav":{"nav":8.7898,"date":"2018-06-12"},"volatility":15.0058,"returns":{"year_1":-1.8573,"year_3":0.0,"year_5":0.0,"inception":-5.0023,"date":"2018-06-13"},"detail_info":"http://www.tatamutualfund.com/downloads/scheme-information-document","start_date":"2015-12-04","face_value":10.0,"fund_type":"Equity","fund_category":"Sectoral/Thematic","plan":"AS N WHEN","expense_ratio":"1.26","fund_name":"Tata Mutual Fund","fund_manager":"Rupesh Patel; Sonam Udasi","crisil_rating":"High","investment_objective":"The investment objective of the scheme is to seek long term capital appreciation by investing atleast 80% of its net assets in equity/equity related instruments of the companies in the pharma \u0026 healthcare sectors in India.","portfolio_turnover":"0.5413"},{"code":"TAIPHDZ-DR","name":"TATA INDIA PHARMA AND HEATHCARE DIVIDEND REINVEST DIRECT PLAN","lump_available":"Y","sip_available":"Y","lump_min":5000.0,"lump_min_additional":1000.0,"lump_max":10000000000000.0,"lump_multiplier":1.0,"sip_min":500.0,"sip_max":1000000000.0,"sip_multiplier":1.0,"sip_dates":["1","2","3","4","5","6","7","8","9","10","11","12","13","14","15","16","17","18","19","20","21","22","23","24","25","26","27","28","29","30"],"purchase_amount_multiplier":"1","redemption_allowed":"Y","redemption_amount_multiple":1.0,"redemption_amount_minimum":500.0,"redemption_quantity_multiple":0.001,"redemption_quantity_minimum":0.001,"category":"Equity","upsizecode_sip_dates":["1","2","3","4","5","6","7","8","9","10","11","12","13","14","15","16","17","18","19","20","21","22","23","24","25","26","27","28","29","30"],"sip_maximum_gap":90,"fund_house":"TATAMutualFund_MF","ISIN":"INF277K011B8","direct":"Y","switch_allowed":"Y","stp_flag":"Y","swp_flag":"Y","sips":[{"sip_frequency":"MONTHLY","sip_dates":["1","2","3","4","5","6","7","8","9","10","11","12","13","14","15","16","17","18","19","20","21","22","23","24","25","26","27","28","29","30"],"sip_minimum_gap":"0","sip_maximum_gap":"90"},{"sip_frequency":"QUARTERLY","sip_dates":["1","2","3","4","5","6","7","8","9","10","11","12","13","14","15","16","17","18","19","20","21","22","23","24","25","26","27","28","29","30"],"sip_minimum_gap":"0","sip_maximum_gap":"90"}],"instant":"N","nav":{"nav":8.8139,"date":"2018-06-13"},"last_nav":{"nav":8.7898,"date":"2018-06-12"},"volatility":15.0058,"returns":{"year_1":-1.8573,"year_3":0.0,"year_5":0.0,"inception":-5.0023,"date":"2018-06-13"},"detail_info":"http://www.tatamutualfund.com/downloads/scheme-information-document","start_date":"2015-12-04","face_value":10.0,"fund_type":"Equity","fund_category":"Sectoral/Thematic","plan":"AS N WHEN","expense_ratio":"1.26","fund_name":"Tata Mutual Fund","fund_manager":"Rupesh Patel; Sonam Udasi","crisil_rating":"High","investment_objective":"The investment objective of the scheme is to seek long term capital appreciation by investing atleast 80% of its net assets in equity/equity related instruments of the companies in the pharma \u0026 healthcare sectors in India.","portfolio_turnover":"0.5413"}]