[{"code":"INBCD1-DP","name":"INDIABULLS BLUECHIP DIVIDEND PAYOUT DIRECT PLAN","lump_available":"Y","sip_available":"N","lump_min":500.0,"lump_min_additional":500.0,"lump_max":10000000000000.0,"lump_multiplier":1.0,"sip_min":500.0,"sip_max":1000000000.0,"sip_multiplier":1.0,"sip_dates":[],"purchase_amount_multiplier":"1","redemption_allowed":"Y","redemption_amount_multiple":1.0,"redemption_amount_minimum":1000.0,"redemption_quantity_multiple":1.0,"redemption_quantity_minimum":100.0,"category":"Equity","upsizecode_sip_dates":[],"sip_maximum_gap":60,"fund_house":"INDIABULLSMUTUALFUND_MF","ISIN":"INF666M01626","direct":"Y","switch_allowed":"Y","stp_flag":"Y","swp_flag":"Y","sips":[{"sip_frequency":"QUARTERLY","sip_dates":["1","5","10","15","20","25"],"sip_minimum_gap":"0","sip_maximum_gap":"60"},{"sip_frequency":"MONTHLY","sip_dates":["1","5","10","15","20","25"],"sip_minimum_gap":"0","sip_maximum_gap":"60"}],"instant":"N","nav":{"nav":12.78,"date":"2018-06-13"},"last_nav":{"nav":12.78,"date":"2018-06-12"},"volatility":25.3589,"returns":{"year_1":-23.3353,"year_3":-2.9881,"year_5":4.4067,"inception":3.1389,"date":"2018-06-13"},"detail_info":"http://www.indiabullsmf.com/sid-sai/#tab-1","start_date":"2013-01-01","face_value":10.0,"fund_type":"Equity","fund_category":"Large Cap Fund","plan":"AS N WHEN","expense_ratio":"0.93","fund_name":"Indiabulls Mutual Fund","fund_manager":"Sumit Bhatnagar","crisil_rating":"High","investment_objective":"To provide long-term capital appreciation from a portfolio that is invested predominantly in equity and equity-related securities of blue chip - large-cap companies.","portfolio_turnover":"2.91"},{"code":"INBCD1-DR","name":"INDIABULLS BLUECHIP DIVIDEND REINVEST DIRECT PLAN","lump_available":"Y","sip_available":"N","lump_min":500.0,"lump_min_additional":500.0,"lump_max":10000000000000.0,"lump_multiplier":1.0,"sip_min":500.0,"sip_max":1000000000.0,"sip_multiplier":1.0,"sip_dates":[],"purchase_amount_multiplier":"1","redemption_allowed":"Y","redemption_amount_multiple":1.0,"redemption_amount_minimum":1000.0,"redemption_quantity_multiple":1.0,"redemption_quantity_minimum":100.0,"category":"Equity","upsizecode_sip_dates":[],"sip_maximum_gap":60,"fund_house":"INDIABULLSMUTUALFUND_MF","ISIN":"INF666M01618","direct":"Y","switch_allowed":"Y","stp_flag":"Y","swp_flag":"Y","sips":[{"sip_frequency":"MONTHLY","sip_dates":["1","5","10","15","20","25"],"sip_minimum_gap":"0","sip_maximum_gap":"60"},{"sip_frequency":"QUARTERLY","sip_dates":["1","5","10","15","20","25"],"sip_minimum_gap":"0","sip_maximum_gap":"60"}],"instant":"N","nav":{"nav":12.78,"date":"2018-06-13"},"last_nav":{"nav":12.78,"date":"2018-06-12"},"volatility":25.3589,"returns":{"year_1":-23.3353,"year_3":-2.9881,"year_5":4.4067,"inception":3.1389,"date":"2018-06-13"},"detail_info":"http://www.indiabullsmf.com/sid-sai/#tab-1","start_date":"2013-01-01","face_value":10.0,"fund_type":"Equity","fund_category":"Large Cap Fund","plan":"AS N WHEN","expense_ratio":"0.93","fund_name":"Indiabulls Mutual Fund","fund_manager":"Sumit Bhatnagar","crisil_rating":"High","investment_objective":"To provide long-term capital appreciation from a portfolio that is invested predominantly in equity and equity-related securities of blue chip - large-cap companies.","portfolio_turnover":"2.91"},{"code":"INBCG1-GR","name":"INDIABULLS BLUECHIP GROWTH DIRECT PLAN","lump_available":"Y","sip_available":"N","lump_min":500.0,"lump_min_additional":500.0,"lump_max":10000000000000.0,"lump_multiplier":1.0,"sip_min":500.0,"sip_max":1000000000.0,"sip_multiplier":1.0,"sip_dates":[],"purchase_amount_multiplier":"1","redemption_allowed":"Y","redemption_amount_multiple":1.0,"redemption_amount_minimum":1000.0,"redemption_quantity_multiple":1.0,"redemption_quantity_minimum":100.0,"category":"Equity","upsizecode_sip_dates":[],"sip_maximum_gap":60,"fund_house":"INDIABULLSMUTUALFUND_MF","ISIN":"INF666M01600","direct":"Y","switch_allowed":"Y","stp_flag":"Y","swp_flag":"Y","sips":[{"sip_frequency":"QUARTERLY","sip_dates":["1","5","10","15","20","25"],"sip_minimum_gap":"0","sip_maximum_gap":"60"},{"sip_frequency":"MONTHLY","sip_dates":["1","5","10","15","20","25"],"sip_minimum_gap":"0","sip_maximum_gap":"60"}],"instant":"N","nav":{"nav":22.02,"date":"2018-06-13"},"last_nav":{"nav":22.02,"date":"2018-06-12"},"volatility":12.1904,"returns":{"year_1":11.8334,"year_3":16.2635,"year_5":16.4018,"inception":13.9738,"date":"2018-06-13"},"detail_info":"http://www.indiabullsmf.com/sid-sai/#tab-1","start_date":"2013-01-01","face_value":10.0,"fund_type":"Equity","fund_category":"Large Cap Fund","plan":"GROWTH","expense_ratio":"0.93","fund_name":"Indiabulls Mutual Fund","fund_manager":"Sumit Bhatnagar","crisil_rating":"High","investment_objective":"To provide long-term capital appreciation from a portfolio that is invested predominantly in equity and equity-related securities of blue chip - large-cap companies.","portfolio_turnover":"2.91"},{"code":"INIFDG-GR","name":"INDIABULLS INCOME GROWTH DIRECT PLAN","lump_available":"Y","sip_available":"N","lump_min":500.0,"lump_min_additional":500.0,"lump_max":10000000000000.0,"lump_multiplier":1.0,"sip_min":500.0,"sip_max":1000000000.0,"sip_multiplier":1.0,"sip_dates":[],"purchase_amount_multiplier":"1","redemption_allowed":"Y","redemption_amount_multiple":1.0,"redemption_amount_minimum":1000.0,"redemption_quantity_multiple":1.0,"redemption_quantity_minimum":100.0,"category":"Debt","upsizecode_sip_dates":[],"sip_maximum_gap":30,"fund_house":"INDIABULLSMUTUALFUND_MF","ISIN":"INF666M01642","direct":"Y","switch_allowed":"Y","stp_flag":"Y","swp_flag":"Y","sips":[{"sip_frequency":"MONTHLY","sip_dates":["1","5","10","15","20","25"],"sip_minimum_gap":"0","sip_maximum_gap":"30"},{"sip_frequency":"QUARTERLY","sip_dates":["1","5","10","15","20","25"],"sip_minimum_gap":"0","sip_maximum_gap":"30"}],"instant":"N","nav":{"nav":15.2028,"date":"2018-06-13"},"last_nav":{"nav":15.1859,"date":"2018-06-12"},"volatility":3.19099,"returns":{"year_1":7.4965,"year_3":8.5257,"year_5":7.7956,"inception":8.2577,"date":"2018-06-13"},"detail_info":"http://www.indiabullsmf.com/sid-sai/#tab-1","start_date":"2013-02-12","face_value":10.0,"fund_type":"Debt","fund_category":"Medium Duration Fund","plan":"GROWTH","expense_ratio":"0.25","fund_name":"Indiabulls Mutual Fund","fund_manager":"Kunal Jain; Karan","crisil_rating":"Moderate","investment_objective":"The primary investment objective of the Scheme is to generate a steady stream of income and medium to long term capital appreciation/gain through investment in fixed income securities such that the Macaulay duration of the portfolio is between 3 years - 4 years. Portfolio Macaulay duration under anticipated adverse situation is 1 year to 4 years. However; there can be no assurance that the investment objective of the Scheme will be achieved.","portfolio_turnover":""},{"code":"INIFDH-DR","name":"INDIABULLS INCOME HALF YEARLY DIVIDEND REINVEST DIRECT PLAN","lump_available":"Y","sip_available":"N","lump_min":500.0,"lump_min_additional":500.0,"lump_max":10000000000000.0,"lump_multiplier":1.0,"sip_min":500.0,"sip_max":1000000000.0,"sip_multiplier":1.0,"sip_dates":[],"purchase_amount_multiplier":"1","redemption_allowed":"Y","redemption_amount_multiple":1.0,"redemption_amount_minimum":1000.0,"redemption_quantity_multiple":1.0,"redemption_quantity_minimum":100.0,"category":"Debt","upsizecode_sip_dates":[],"sip_maximum_gap":30,"fund_house":"INDIABULLSMUTUALFUND_MF","ISIN":"INF666M01675","direct":"Y","switch_allowed":"Y","stp_flag":"Y","swp_flag":"Y","sips":[{"sip_frequency":"QUARTERLY","sip_dates":["1","5","10","15","20","25"],"sip_minimum_gap":"0","sip_maximum_gap":"30"},{"sip_frequency":"MONTHLY","sip_dates":["1","5","10","15","20","25"],"sip_minimum_gap":"0","sip_maximum_gap":"30"}],"instant":"N","nav":{"nav":13.012,"date":"2018-06-13"},"last_nav":{"nav":12.9974,"date":"2018-06-12"},"volatility":3.19067,"returns":{"year_1":7.5168,"year_3":8.5307,"year_5":5.6091,"inception":6.122,"date":"2018-06-13"},"detail_info":"http://www.indiabullsmf.com/sid-sai/#tab-1","start_date":"2013-02-12","face_value":10.0,"fund_type":"Debt","fund_category":"Medium Duration Fund","plan":"DIVIDEND SEMI-ANNUALLY","expense_ratio":"0.25","fund_name":"Indiabulls Mutual Fund","fund_manager":"Kunal Jain; Karan","crisil_rating":"Moderate","investment_objective":"The primary investment objective of the Scheme is to generate a steady stream of income and medium to long term capital appreciation/gain through investment in fixed income securities such that the Macaulay duration of the portfolio is between 3 years - 4 years. Portfolio Macaulay duration under anticipated adverse situation is 1 year to 4 years. However; there can be no assurance that the investment objective of the Scheme will be achieved.","portfolio_turnover":""},{"code":"INIFDM-DP","name":"INDIABULLS INCOME MONTHLY DIVIDEND PAYOUT DIRECT PLAN","lump_available":"Y","sip_available":"N","lump_min":500.0,"lump_min_additional":500.0,"lump_max":10000000000000.0,"lump_multiplier":1.0,"sip_min":500.0,"sip_max":1000000000.0,"sip_multiplier":1.0,"sip_dates":[],"purchase_amount_multiplier":"1","redemption_allowed":"Y","redemption_amount_multiple":1.0,"redemption_amount_minimum":1000.0,"redemption_quantity_multiple":1.0,"redemption_quantity_minimum":100.0,"category":"Debt","upsizecode_sip_dates":[],"sip_maximum_gap":30,"fund_house":"INDIABULLSMUTUALFUND_MF","ISIN":"INF666M01683","direct":"Y","switch_allowed":"Y","stp_flag":"Y","swp_flag":"Y","sips":[{"sip_frequency":"QUARTERLY","sip_dates":["1","5","10","15","20","25"],"sip_minimum_gap":"0","sip_maximum_gap":"30"},{"sip_frequency":"MONTHLY","sip_dates":["1","5","10","15","20","25"],"sip_minimum_gap":"0","sip_maximum_gap":"30"}],"instant":"N","nav":{"nav":10.5436,"date":"2018-06-13"},"last_nav":{"nav":10.5319,"date":"2018-06-12"},"volatility":5.09474,"returns":{"year_1":3.2738,"year_3":4.1297,"year_5":3.0852,"inception":3.5102,"date":"2018-06-13"},"detail_info":"http://www.indiabullsmf.com/sid-sai/#tab-1","start_date":"2013-02-12","face_value":10.0,"fund_type":"Debt","fund_category":"Medium Duration Fund","plan":"DIVIDEND MONTHLY","expense_ratio":"0.25","fund_name":"Indiabulls Mutual Fund","fund_manager":"Kunal Jain; Karan","crisil_rating":"Moderate","investment_objective":"The primary investment objective of the Scheme is to generate a steady stream of income and medium to long term capital appreciation/gain through investment in fixed income securities such that the Macaulay duration of the portfolio is between 3 years - 4 years. Portfolio Macaulay duration under anticipated adverse situation is 1 year to 4 years. However; there can be no assurance that the investment objective of the Scheme will be achieved.","portfolio_turnover":""},{"code":"INIFDM-DR","name":"INDIABULLS INCOME MONTHLY DIVIDEND REINVEST DIRECT PLAN","lump_available":"Y","sip_available":"N","lump_min":500.0,"lump_min_additional":500.0,"lump_max":10000000000000.0,"lump_multiplier":1.0,"sip_min":500.0,"sip_max":1000000000.0,"sip_multiplier":1.0,"sip_dates":[],"purchase_amount_multiplier":"1","redemption_allowed":"Y","redemption_amount_multiple":1.0,"redemption_amount_minimum":1000.0,"redemption_quantity_multiple":1.0,"redemption_quantity_minimum":100.0,"category":"Debt","upsizecode_sip_dates":[],"sip_maximum_gap":30,"fund_house":"INDIABULLSMUTUALFUND_MF","ISIN":"INF666M01659","direct":"Y","switch_allowed":"Y","stp_flag":"Y","swp_flag":"Y","sips":[{"sip_frequency":"QUARTERLY","sip_dates":["1","5","10","15","20","25"],"sip_minimum_gap":"0","sip_maximum_gap":"30"},{"sip_frequency":"MONTHLY","sip_dates":["1","5","10","15","20","25"],"sip_minimum_gap":"0","sip_maximum_gap":"30"}],"instant":"N","nav":{"nav":10.5436,"date":"2018-06-13"},"last_nav":{"nav":10.5319,"date":"2018-06-12"},"volatility":5.09474,"returns":{"year_1":3.2738,"year_3":4.1297,"year_5":3.0852,"inception":3.5102,"date":"2018-06-13"},"detail_info":"http://www.indiabullsmf.com/sid-sai/#tab-1","start_date":"2013-02-12","face_value":10.0,"fund_type":"Debt","fund_category":"Medium Duration Fund","plan":"DIVIDEND MONTHLY","expense_ratio":"0.25","fund_name":"Indiabulls Mutual Fund","fund_manager":"Kunal Jain; Karan","crisil_rating":"Moderate","investment_objective":"The primary investment objective of the Scheme is to generate a steady stream of income and medium to long term capital appreciation/gain through investment in fixed income securities such that the Macaulay duration of the portfolio is between 3 years - 4 years. Portfolio Macaulay duration under anticipated adverse situation is 1 year to 4 years. However; there can be no assurance that the investment objective of the Scheme will be achieved.","portfolio_turnover":""},{"code":"INIFDQ-DP","name":"INDIABULLS INCOME QUARTERLY DIVIDEND PAYOUT DIRECT PLAN","lump_available":"Y","sip_available":"N","lump_min":500.0,"lump_min_additional":500.0,"lump_max":10000000000000.0,"lump_multiplier":1.0,"sip_min":500.0,"sip_max":1000000000.0,"sip_multiplier":1.0,"sip_dates":[],"purchase_amount_multiplier":"1","redemption_allowed":"Y","redemption_amount_multiple":1.0,"redemption_amount_minimum":1000.0,"redemption_quantity_multiple":1.0,"redemption_quantity_minimum":100.0,"category":"Debt","upsizecode_sip_dates":[],"sip_maximum_gap":30,"fund_house":"INDIABULLSMUTUALFUND_MF","ISIN":"INF666M01691","direct":"Y","switch_allowed":"Y","stp_flag":"Y","swp_flag":"Y","sips":[{"sip_frequency":"QUARTERLY","sip_dates":["1","5","10","15","20","25"],"sip_minimum_gap":"0","sip_maximum_gap":"30"},{"sip_frequency":"MONTHLY","sip_dates":["1","5","10","15","20","25"],"sip_minimum_gap":"0","sip_maximum_gap":"30"}],"instant":"N","nav":{"nav":13.0439,"date":"2018-06-13"},"last_nav":{"nav":13.0294,"date":"2018-06-12"},"volatility":3.19127,"returns":{"year_1":7.5165,"year_3":8.5322,"year_5":5.0469,"inception":5.5867,"date":"2018-06-13"},"detail_info":"http://www.indiabullsmf.com/sid-sai/#tab-1","start_date":"2013-02-12","face_value":10.0,"fund_type":"Debt","fund_category":"Medium Duration Fund","plan":"DIVIDEND QUARTERLY","expense_ratio":"0.25","fund_name":"Indiabulls Mutual Fund","fund_manager":"Kunal Jain; Karan","crisil_rating":"Moderate","investment_objective":"The primary investment objective of the Scheme is to generate a steady stream of income and medium to long term capital appreciation/gain through investment in fixed income securities such that the Macaulay duration of the portfolio is between 3 years - 4 years. Portfolio Macaulay duration under anticipated adverse situation is 1 year to 4 years. However; there can be no assurance that the investment objective of the Scheme will be achieved.","portfolio_turnover":""},{"code":"INIFDQ-DR","name":"INDIABULLS INCOME QUARTERLY DIVIDEND REINVEST DIRECT PLAN","lump_available":"Y","sip_available":"N","lump_min":500.0,"lump_min_additional":500.0,"lump_max":10000000000000.0,"lump_multiplier":1.0,"sip_min":500.0,"sip_max":1000000000.0,"sip_multiplier":1.0,"sip_dates":[],"purchase_amount_multiplier":"1","redemption_allowed":"Y","redemption_amount_multiple":1.0,"redemption_amount_minimum":1000.0,"redemption_quantity_multiple":1.0,"redemption_quantity_minimum":100.0,"category":"Debt","upsizecode_sip_dates":[],"sip_maximum_gap":30,"fund_house":"INDIABULLSMUTUALFUND_MF","ISIN":"INF666M01667","direct":"Y","switch_allowed":"Y","stp_flag":"Y","swp_flag":"Y","sips":[{"sip_frequency":"QUARTERLY","sip_dates":["1","5","10","15","20","25"],"sip_minimum_gap":"0","sip_maximum_gap":"30"},{"sip_frequency":"MONTHLY","sip_dates":["1","5","10","15","20","25"],"sip_minimum_gap":"0","sip_maximum_gap":"30"}],"instant":"N","nav":{"nav":13.0439,"date":"2018-06-13"},"last_nav":{"nav":13.0294,"date":"2018-06-12"},"volatility":3.19127,"returns":{"year_1":7.5165,"year_3":8.5322,"year_5":5.0469,"inception":5.5867,"date":"2018-06-13"},"detail_info":"http://www.indiabullsmf.com/sid-sai/#tab-1","start_date":"2013-02-12","face_value":10.0,"fund_type":"Debt","fund_category":"Medium Duration Fund","plan":"DIVIDEND QUARTERLY","expense_ratio":"0.25","fund_name":"Indiabulls Mutual Fund","fund_manager":"Kunal Jain; Karan","crisil_rating":"Moderate","investment_objective":"The primary investment objective of the Scheme is to generate a steady stream of income and medium to long term capital appreciation/gain through investment in fixed income securities such that the Macaulay duration of the portfolio is between 3 years - 4 years. Portfolio Macaulay duration under anticipated adverse situation is 1 year to 4 years. However; there can be no assurance that the investment objective of the Scheme will be achieved.","portfolio_turnover":""},{"code":"INUSD1-DR","name":"INDIABULLS ULTRA SHORT TERM DAILY DIVIDEND REINVEST DIRECT PLAN","lump_available":"Y","sip_available":"N","lump_min":500.0,"lump_min_additional":500.0,"lump_max":10000000000000.0,"lump_multiplier":1.0,"sip_min":500.0,"sip_max":1000000000.0,"sip_multiplier":1.0,"sip_dates":[],"purchase_amount_multiplier":"1","redemption_allowed":"Y","redemption_amount_multiple":1.0,"redemption_amount_minimum":1000.0,"redemption_quantity_multiple":1.0,"redemption_quantity_minimum":1.0,"category":"Debt","upsizecode_sip_dates":[],"sip_maximum_gap":30,"fund_house":"INDIABULLSMUTUALFUND_MF","ISIN":"INF666M01634","direct":"Y","switch_allowed":"Y","stp_flag":"Y","swp_flag":"Y","sips":[{"sip_frequency":"QUARTERLY","sip_dates":["1","5","10","15","20","25"],"sip_minimum_gap":"0","sip_maximum_gap":"30"},{"sip_frequency":"MONTHLY","sip_dates":["1","5","10","15","20","25"],"sip_minimum_gap":"0","sip_maximum_gap":"30"}],"instant":"N","nav":{"nav":1004.35,"date":"2018-06-13"},"last_nav":{"nav":1004.35,"date":"2018-06-12"},"volatility":0.0751073,"returns":{"year_1":4.6159,"year_3":5.5281,"year_5":4.5978,"inception":4.4902,"date":"2018-06-13"},"detail_info":"http://www.indiabullsmf.com/sid-sai/#tab-1","start_date":"2013-01-01","face_value":1000.0,"fund_type":"Debt","fund_category":"Ultra Short Duration Fund","plan":"DIVIDEND DAILY","expense_ratio":"0.29","fund_name":"Indiabulls Mutual Fund","fund_manager":"Malay Shah","crisil_rating":"Moderately Low","investment_objective":"To Provide Liquidity with returns commensurate with low risk through a portfolio of money market and debt securities such that the Macaulay duration of the portfolio is between 3 - 6 months.","portfolio_turnover":""}]