[{"code":"PR2FD1-GR","name":"PGIM India Ultra Short Term Growth Direct Plan","short_name":"PGIM India UST","lump_available":"Y","sip_available":"Y","lump_min":5000.0,"lump_min_additional":1000.0,"lump_max":10000000000000.0,"lump_multiplier":1.0,"sip_min":500.0,"sip_max":999999999.0,"sip_multiplier":1.0,"sip_dates":["1","2","3","4","5","6","7","8","9","10","11","12","13","14","15","16","17","18","19","20","21","22","23","24","25","26","27","28"],"redemption_allowed":"Y","redemption_amount_multiple":1.0,"redemption_amount_minimum":100.0,"redemption_quantity_multiple":0.001,"redemption_quantity_minimum":0.1,"category":"Debt - Bonds","upsizecode_sip_dates":["1","2","3","4","5","6","7","8","9","10","11","12","13","14","15","16","17","18","19","20","21","22","23","24","25","26","27","28"],"sip_maximum_gap":60,"fund_house":"PGIMINDIAMUTUALFUND_MF","fund_name":"PGIM India Mutual Fund","short_code":"pgim","detail_info":"https://www.pgimindiamf.com/forms-and-updates/sid-and-sai","ISIN":"INF223J01QO7","direct":"Y","switch_allowed":"Y","stp_flag":"Y","swp_flag":"Y","sips":[{"sip_frequency":"QUARTERLY","sip_dates":["1","2","3","4","5","6","7","8","9","10","11","12","13","14","15","16","17","18","19","20","21","22","23","24","25","26","27","28"],"sip_minimum_gap":"0","sip_maximum_gap":"60"},{"sip_frequency":"MONTHLY","sip_dates":["1","2","3","4","5","6","7","8","9","10","11","12","13","14","15","16","17","18","19","20","21","22","23","24","25","26","27","28"],"sip_minimum_gap":"0","sip_maximum_gap":"60"}],"instant":"N","reinvestment":"Z","tags":["top_searched"],"slug":"pgim-india-ultra-short-term-growth--PR2FD1-GR","channel_partner_code":"1292FD1","tax_period":1095,"nav":{"nav":26.0516,"date":"2020-03-12"},"last_nav":{"nav":26.0714,"date":"2020-03-11"},"jan_31_nav":21.0323,"volatility":0.916841,"returns":{"year_1":13.4196,"year_3":9.5478,"year_5":9.2127,"inception":9.4214,"date":"2020-03-12"},"start_date":"2013-01-01","face_value":10.0,"fund_type":"Debt","fund_category":"Ultra Short Duration Fund","plan":"GROWTH","expense_ratio":"0.26","expense_ratio_date":"2020-01-31","fund_manager":"Kumaresh Ramakrishnan; Kunal Jain","crisil_rating":"Moderately Low","investment_objective":"To provide liquidity and seek to generate returns by investing in a mix of short term debt and money market instruments. However; there can be no assurance that the investment objective of the Scheme will be achieved. The Scheme does not guarantee/indicate any returns.","portfolio_turnover":null,"maturity_type":"Open Ended","aum":1420},{"code":"PR2FD5-DP","name":"PGIM India Ultra Short Term Monthly Dividend Payout Direct Plan","short_name":"PGIM India UST Monthly Dividend Payout","lump_available":"Y","sip_available":"Y","lump_min":5000.0,"lump_min_additional":1000.0,"lump_max":10000000000000.0,"lump_multiplier":1.0,"sip_min":500.0,"sip_max":999999999.0,"sip_multiplier":1.0,"sip_dates":["1","2","3","4","5","6","7","8","9","10","11","12","13","14","15","16","17","18","19","20","21","22","23","24","25","26","27","28"],"redemption_allowed":"Y","redemption_amount_multiple":1.0,"redemption_amount_minimum":100.0,"redemption_quantity_multiple":0.001,"redemption_quantity_minimum":0.1,"category":"Debt - Bonds","upsizecode_sip_dates":["1","2","3","4","5","6","7","8","9","10","11","12","13","14","15","16","17","18","19","20","21","22","23","24","25","26","27","28"],"sip_maximum_gap":60,"fund_house":"PGIMINDIAMUTUALFUND_MF","fund_name":"PGIM India Mutual Fund","short_code":"pgim","detail_info":"https://www.pgimindiamf.com/forms-and-updates/sid-and-sai","ISIN":"INF223J01QP4","direct":"Y","switch_allowed":"Y","stp_flag":"Y","swp_flag":"Y","sips":[{"sip_frequency":"MONTHLY","sip_dates":["1","2","3","4","5","6","7","8","9","10","11","12","13","14","15","16","17","18","19","20","21","22","23","24","25","26","27","28"],"sip_minimum_gap":"0","sip_maximum_gap":"60"},{"sip_frequency":"QUARTERLY","sip_dates":["1","2","3","4","5","6","7","8","9","10","11","12","13","14","15","16","17","18","19","20","21","22","23","24","25","26","27","28"],"sip_minimum_gap":"0","sip_maximum_gap":"60"}],"instant":"N","reinvestment":"N","tags":[],"slug":"pgim-india-ultra-short-term-monthly-dividend-payout--PR2FD5-DP","channel_partner_code":"1292FD5","tax_period":1095,"nav":{"nav":11.9384,"date":"2020-03-12"},"last_nav":{"nav":11.9474,"date":"2020-03-11"},"jan_31_nav":10.9848,"volatility":2.08356,"returns":{"year_1":11.3785,"year_3":7.68,"year_5":7.1854,"inception":7.6548,"date":"2020-03-12"},"start_date":"2013-01-01","face_value":10.0,"fund_type":"Debt","fund_category":"Ultra Short Duration Fund","plan":"DIVIDEND MONTHLY","expense_ratio":"0.26","expense_ratio_date":"2020-01-31","fund_manager":"Kumaresh Ramakrishnan; Kunal Jain","crisil_rating":"Moderately Low","investment_objective":"To provide liquidity and seek to generate returns by investing in a mix of short term debt and money market instruments. However; there can be no assurance that the investment objective of the Scheme will be achieved. The Scheme does not guarantee/indicate any returns.","portfolio_turnover":null,"maturity_type":"Open Ended","aum":1420},{"code":"PR2FD5-DR","name":"PGIM India Ultra Short Term Monthly Dividend Reinvest Direct Plan","short_name":"PGIM India UST Monthly Dividend Reinvest","lump_available":"Y","sip_available":"Y","lump_min":5000.0,"lump_min_additional":1000.0,"lump_max":10000000000000.0,"lump_multiplier":1.0,"sip_min":500.0,"sip_max":999999999.0,"sip_multiplier":1.0,"sip_dates":["1","2","3","4","5","6","7","8","9","10","11","12","13","14","15","16","17","18","19","20","21","22","23","24","25","26","27","28"],"redemption_allowed":"Y","redemption_amount_multiple":1.0,"redemption_amount_minimum":100.0,"redemption_quantity_multiple":0.001,"redemption_quantity_minimum":0.1,"category":"Debt - Bonds","upsizecode_sip_dates":["1","2","3","4","5","6","7","8","9","10","11","12","13","14","15","16","17","18","19","20","21","22","23","24","25","26","27","28"],"sip_maximum_gap":60,"fund_house":"PGIMINDIAMUTUALFUND_MF","fund_name":"PGIM India Mutual Fund","short_code":"pgim","detail_info":"https://www.pgimindiamf.com/forms-and-updates/sid-and-sai","ISIN":"INF223J01QQ2","direct":"Y","switch_allowed":"Y","stp_flag":"Y","swp_flag":"Y","sips":[{"sip_frequency":"QUARTERLY","sip_dates":["1","2","3","4","5","6","7","8","9","10","11","12","13","14","15","16","17","18","19","20","21","22","23","24","25","26","27","28"],"sip_minimum_gap":"0","sip_maximum_gap":"60"},{"sip_frequency":"MONTHLY","sip_dates":["1","2","3","4","5","6","7","8","9","10","11","12","13","14","15","16","17","18","19","20","21","22","23","24","25","26","27","28"],"sip_minimum_gap":"0","sip_maximum_gap":"60"}],"instant":"N","reinvestment":"Y","tags":[],"slug":"pgim-india-ultra-short-term-monthly-dividend-reinvest--PR2FD5-DR","channel_partner_code":"1292FD5","tax_period":1095,"nav":{"nav":11.9384,"date":"2020-03-12"},"last_nav":{"nav":11.9474,"date":"2020-03-11"},"jan_31_nav":10.9848,"volatility":2.08356,"returns":{"year_1":11.3785,"year_3":7.68,"year_5":7.1854,"inception":7.6548,"date":"2020-03-12"},"start_date":"2013-01-01","face_value":10.0,"fund_type":"Debt","fund_category":"Ultra Short Duration Fund","plan":"DIVIDEND MONTHLY","expense_ratio":"0.26","expense_ratio_date":"2020-01-31","fund_manager":"Kumaresh Ramakrishnan; Kunal Jain","crisil_rating":"Moderately Low","investment_objective":"To provide liquidity and seek to generate returns by investing in a mix of short term debt and money market instruments. However; there can be no assurance that the investment objective of the Scheme will be achieved. The Scheme does not guarantee/indicate any returns.","portfolio_turnover":null,"maturity_type":"Open Ended","aum":1420},{"code":"PR2FD4-DP","name":"PGIM India Ultra Short Term Weekly Dividend Payout Direct Plan","short_name":"PGIM India UST Weekly Dividend Payout","lump_available":"Y","sip_available":"Y","lump_min":5000.0,"lump_min_additional":1000.0,"lump_max":10000000000000.0,"lump_multiplier":1.0,"sip_min":500.0,"sip_max":999999999.0,"sip_multiplier":1.0,"sip_dates":["1","2","3","4","5","6","7","8","9","10","11","12","13","14","15","16","17","18","19","20","21","22","23","24","25","26","27","28"],"redemption_allowed":"Y","redemption_amount_multiple":1.0,"redemption_amount_minimum":100.0,"redemption_quantity_multiple":0.001,"redemption_quantity_minimum":0.1,"category":"Debt - Bonds","upsizecode_sip_dates":["1","2","3","4","5","6","7","8","9","10","11","12","13","14","15","16","17","18","19","20","21","22","23","24","25","26","27","28"],"sip_maximum_gap":60,"fund_house":"PGIMINDIAMUTUALFUND_MF","fund_name":"PGIM India Mutual Fund","short_code":"pgim","detail_info":"https://www.pgimindiamf.com/forms-and-updates/sid-and-sai","ISIN":"INF223J01QR0","direct":"Y","switch_allowed":"Y","stp_flag":"Y","swp_flag":"Y","sips":[{"sip_frequency":"QUARTERLY","sip_dates":["1","2","3","4","5","6","7","8","9","10","11","12","13","14","15","16","17","18","19","20","21","22","23","24","25","26","27","28"],"sip_minimum_gap":"0","sip_maximum_gap":"60"},{"sip_frequency":"MONTHLY","sip_dates":["1","2","3","4","5","6","7","8","9","10","11","12","13","14","15","16","17","18","19","20","21","22","23","24","25","26","27","28"],"sip_minimum_gap":"0","sip_maximum_gap":"60"}],"instant":"N","reinvestment":"N","tags":[],"slug":"pgim-india-ultra-short-term-weekly-dividend-payout--PR2FD4-DP","channel_partner_code":"1292FD4","tax_period":1095,"nav":{"nav":10.2651,"date":"2020-03-12"},"last_nav":{"nav":10.2729,"date":"2020-03-11"},"jan_31_nav":10.278,"volatility":1.45563,"returns":{"year_1":9.3474,"year_3":6.6002,"year_5":6.38,"inception":6.7132,"date":"2020-03-12"},"start_date":"2013-01-01","face_value":10.0,"fund_type":"Debt","fund_category":"Ultra Short Duration Fund","plan":"DIVIDEND WEEKLY","expense_ratio":"0.26","expense_ratio_date":"2020-01-31","fund_manager":"Kumaresh Ramakrishnan; Kunal Jain","crisil_rating":"Moderately Low","investment_objective":"To provide liquidity and seek to generate returns by investing in a mix of short term debt and money market instruments. However; there can be no assurance that the investment objective of the Scheme will be achieved. The Scheme does not guarantee/indicate any returns.","portfolio_turnover":null,"maturity_type":"Open Ended","aum":1420},{"code":"PR2FD4-DR","name":"PGIM India Ultra Short Term Weekly Dividend Reinvest Direct Plan","short_name":"PGIM India UST Weekly Dividend Reinvest","lump_available":"Y","sip_available":"Y","lump_min":5000.0,"lump_min_additional":1000.0,"lump_max":10000000000000.0,"lump_multiplier":1.0,"sip_min":500.0,"sip_max":999999999.0,"sip_multiplier":1.0,"sip_dates":["1","2","3","4","5","6","7","8","9","10","11","12","13","14","15","16","17","18","19","20","21","22","23","24","25","26","27","28"],"redemption_allowed":"Y","redemption_amount_multiple":1.0,"redemption_amount_minimum":100.0,"redemption_quantity_multiple":0.001,"redemption_quantity_minimum":0.1,"category":"Debt - Bonds","upsizecode_sip_dates":["1","2","3","4","5","6","7","8","9","10","11","12","13","14","15","16","17","18","19","20","21","22","23","24","25","26","27","28"],"sip_maximum_gap":60,"fund_house":"PGIMINDIAMUTUALFUND_MF","fund_name":"PGIM India Mutual Fund","short_code":"pgim","detail_info":"https://www.pgimindiamf.com/forms-and-updates/sid-and-sai","ISIN":"INF223J01QS8","direct":"Y","switch_allowed":"Y","stp_flag":"Y","swp_flag":"Y","sips":[{"sip_frequency":"MONTHLY","sip_dates":["1","2","3","4","5","6","7","8","9","10","11","12","13","14","15","16","17","18","19","20","21","22","23","24","25","26","27","28"],"sip_minimum_gap":"0","sip_maximum_gap":"60"},{"sip_frequency":"QUARTERLY","sip_dates":["1","2","3","4","5","6","7","8","9","10","11","12","13","14","15","16","17","18","19","20","21","22","23","24","25","26","27","28"],"sip_minimum_gap":"0","sip_maximum_gap":"60"}],"instant":"N","reinvestment":"Y","tags":[],"slug":"pgim-india-ultra-short-term-weekly-dividend-reinvest--PR2FD4-DR","channel_partner_code":"1292FD4","tax_period":1095,"nav":{"nav":10.2651,"date":"2020-03-12"},"last_nav":{"nav":10.2729,"date":"2020-03-11"},"jan_31_nav":10.278,"volatility":1.45563,"returns":{"year_1":9.3474,"year_3":6.6002,"year_5":6.38,"inception":6.7132,"date":"2020-03-12"},"start_date":"2013-01-01","face_value":10.0,"fund_type":"Debt","fund_category":"Ultra Short Duration Fund","plan":"DIVIDEND WEEKLY","expense_ratio":"0.26","expense_ratio_date":"2020-01-31","fund_manager":"Kumaresh Ramakrishnan; Kunal Jain","crisil_rating":"Moderately Low","investment_objective":"To provide liquidity and seek to generate returns by investing in a mix of short term debt and money market instruments. However; there can be no assurance that the investment objective of the Scheme will be achieved. The Scheme does not guarantee/indicate any returns.","portfolio_turnover":null,"maturity_type":"Open Ended","aum":1420},{"code":"PR2FD6-DP","name":"PGIM India Ultra Short Term Quarterly Dividend Payout Direct Plan","short_name":"PGIM India UST Quarterly Dividend Payout","lump_available":"N","sip_available":"N","lump_min":5000.0,"lump_min_additional":1000.0,"lump_max":10000000000000.0,"lump_multiplier":1.0,"sip_min":500.0,"sip_max":999999999.0,"sip_multiplier":1.0,"sip_dates":[],"redemption_allowed":"N","redemption_amount_multiple":1.0,"redemption_amount_minimum":100.0,"redemption_quantity_multiple":0.001,"redemption_quantity_minimum":0.1,"category":"Debt - Bonds","upsizecode_sip_dates":[],"sip_maximum_gap":60,"fund_house":"PGIMINDIAMUTUALFUND_MF","fund_name":"PGIM India Mutual Fund","short_code":"pgim","detail_info":"https://www.pgimindiamf.com/forms-and-updates/sid-and-sai","ISIN":"INF223J01QT6","direct":"Y","switch_allowed":"N","stp_flag":"N","swp_flag":"N","sips":[{"sip_frequency":"MONTHLY","sip_dates":["1","2","3","4","5","6","7","8","9","10","11","12","13","14","15","16","17","18","19","20","21","22","23","24","25","26","27","28"],"sip_minimum_gap":"0","sip_maximum_gap":"60"},{"sip_frequency":"QUARTERLY","sip_dates":["1","2","3","4","5","6","7","8","9","10","11","12","13","14","15","16","17","18","19","20","21","22","23","24","25","26","27","28"],"sip_minimum_gap":"0","sip_maximum_gap":"60"}],"instant":"N","reinvestment":"N","tags":[],"slug":"pgim-india-ultra-short-term-quarterly-dividend-payout--PR2FD6-DP","channel_partner_code":"1292FD6","tax_period":1095,"nav":{"nav":11.2976,"date":"2019-07-28"},"last_nav":{"nav":11.2894,"date":"2019-07-27"},"jan_31_nav":10.8447,"volatility":3.70008,"returns":{"year_1":0.0,"year_3":0.0,"year_5":0.0,"inception":0.0,"date":"2019-08-20"},"start_date":"2013-01-01","face_value":10.0,"fund_type":"Debt","fund_category":"Ultra Short Duration Fund","plan":"DIVIDEND QUARTERLY","expense_ratio":"0.33","expense_ratio_date":"2019-07-31","fund_manager":"Kumaresh Ramakrishnan; Kunal Jain","crisil_rating":"Moderately Low","investment_objective":"To provide liquidity and seek to generate returns by investing in a mix of short term debt and money market instruments. However; there can be no assurance that the investment objective of the Scheme will be achieved. The Scheme does not guarantee/indicate any returns.","portfolio_turnover":null,"maturity_type":"Open Ended","aum":500},{"code":"PR2FD6-DR","name":"PGIM India Ultra Short Term Quarterly Dividend Reinvest Direct Plan","short_name":"PGIM India UST Quarterly Dividend Reinvest","lump_available":"N","sip_available":"N","lump_min":5000.0,"lump_min_additional":1000.0,"lump_max":10000000000000.0,"lump_multiplier":1.0,"sip_min":500.0,"sip_max":999999999.0,"sip_multiplier":1.0,"sip_dates":[],"redemption_allowed":"N","redemption_amount_multiple":1.0,"redemption_amount_minimum":100.0,"redemption_quantity_multiple":0.001,"redemption_quantity_minimum":0.1,"category":"Debt - Bonds","upsizecode_sip_dates":[],"sip_maximum_gap":60,"fund_house":"PGIMINDIAMUTUALFUND_MF","fund_name":"PGIM India Mutual Fund","short_code":"pgim","detail_info":"https://www.pgimindiamf.com/forms-and-updates/sid-and-sai","ISIN":"INF223J01QU4","direct":"Y","switch_allowed":"N","stp_flag":"N","swp_flag":"N","sips":[{"sip_frequency":"QUARTERLY","sip_dates":["1","2","3","4","5","6","7","8","9","10","11","12","13","14","15","16","17","18","19","20","21","22","23","24","25","26","27","28"],"sip_minimum_gap":"0","sip_maximum_gap":"60"},{"sip_frequency":"MONTHLY","sip_dates":["1","2","3","4","5","6","7","8","9","10","11","12","13","14","15","16","17","18","19","20","21","22","23","24","25","26","27","28"],"sip_minimum_gap":"0","sip_maximum_gap":"60"}],"instant":"N","reinvestment":"Y","tags":[],"slug":"pgim-india-ultra-short-term-quarterly-dividend-reinvest--PR2FD6-DR","channel_partner_code":"1292FD6","tax_period":1095,"nav":{"nav":11.2976,"date":"2019-07-28"},"last_nav":{"nav":11.2894,"date":"2019-07-27"},"jan_31_nav":10.8447,"volatility":3.70008,"returns":{"year_1":0.0,"year_3":0.0,"year_5":0.0,"inception":0.0,"date":"2019-08-20"},"start_date":"2013-01-01","face_value":10.0,"fund_type":"Debt","fund_category":"Ultra Short Duration Fund","plan":"DIVIDEND QUARTERLY","expense_ratio":"0.33","expense_ratio_date":"2019-07-31","fund_manager":"Kumaresh Ramakrishnan; Kunal Jain","crisil_rating":"Moderately Low","investment_objective":"To provide liquidity and seek to generate returns by investing in a mix of short term debt and money market instruments. However; there can be no assurance that the investment objective of the Scheme will be achieved. The Scheme does not guarantee/indicate any returns.","portfolio_turnover":null,"maturity_type":"Open Ended","aum":500},{"code":"PRAFD2-DP","name":"PGIM India Hybrid Debt Monthly Dividend Payout Direct Plan","short_name":"PGIM India Hybrid Debt Monthly Dividend Payout","lump_available":"N","sip_available":"N","lump_min":5000.0,"lump_min_additional":1000.0,"lump_max":10000000000000.0,"lump_multiplier":1.0,"sip_min":500.0,"sip_max":999999999.0,"sip_multiplier":1.0,"sip_dates":[],"redemption_allowed":"N","redemption_amount_multiple":1.0,"redemption_amount_minimum":100.0,"redemption_quantity_multiple":0.1,"redemption_quantity_minimum":0.1,"category":"Debt - Bonds","upsizecode_sip_dates":[],"sip_maximum_gap":60,"fund_house":"PGIMINDIAMUTUALFUND_MF","fund_name":"PGIM India Mutual Fund","short_code":"pgim","detail_info":"http://www.dhflpramericamf.com/downloads/sid-and-sai","ISIN":"INF223J01RB2","direct":"Y","switch_allowed":"N","stp_flag":"N","swp_flag":"N","sips":[{"sip_frequency":"QUARTERLY","sip_dates":["1","2","3","4","5","6","7","8","9","10","11","12","13","14","15","16","17","18","19","20","21","22","23","24","25","26","27","28"],"sip_minimum_gap":"0","sip_maximum_gap":"60"},{"sip_frequency":"MONTHLY","sip_dates":["1","2","3","4","5","6","7","8","9","10","11","12","13","14","15","16","17","18","19","20","21","22","23","24","25","26","27","28"],"sip_minimum_gap":"0","sip_maximum_gap":"60"}],"instant":"N","reinvestment":"N","tags":[],"slug":"pgim-india-hybrid-debt-monthly-dividend-payout--PRAFD2-DP","channel_partner_code":"129AFD2","tax_period":1095,"nav":{"nav":10.9781,"date":"2019-07-28"},"last_nav":{"nav":10.9768,"date":"2019-07-27"},"jan_31_nav":10.4831,"volatility":3.34918,"returns":{"year_1":4.9347,"year_3":0.0,"year_5":0.0,"inception":5.6552,"date":"2019-07-26"},"start_date":"2017-04-17","face_value":10.0,"fund_type":"Hybrid","fund_category":"Conservative Hybrid Fund","plan":"DIVIDEND MONTHLY","expense_ratio":"0.71","expense_ratio_date":"2019-06-30","fund_manager":"Kumaresh Ramakrishnan; Alok Agarwal","crisil_rating":"Moderate","investment_objective":"The objective of Scheme is to seek to generate returns through investment primarily in Debt and Money Market Instruments and to generate capital appreciation by investing in equity and equity related instruments. However; there is no assurance that the investment objective of the Scheme will be realized and the Scheme does not assure or guarantee any returns.","portfolio_turnover":"1.11","maturity_type":"Open Ended","aum":180},{"code":"PRAFD2-DR","name":"PGIM India Hybrid Debt Monthly Dividend Reinvest Direct Plan","short_name":"PGIM India Hybrid Debt Monthly Dividend Reinvest","lump_available":"N","sip_available":"N","lump_min":5000.0,"lump_min_additional":1000.0,"lump_max":10000000000000.0,"lump_multiplier":1.0,"sip_min":500.0,"sip_max":999999999.0,"sip_multiplier":1.0,"sip_dates":[],"redemption_allowed":"N","redemption_amount_multiple":1.0,"redemption_amount_minimum":100.0,"redemption_quantity_multiple":0.1,"redemption_quantity_minimum":0.1,"category":"Debt - Bonds","upsizecode_sip_dates":[],"sip_maximum_gap":60,"fund_house":"PGIMINDIAMUTUALFUND_MF","fund_name":"PGIM India Mutual Fund","short_code":"pgim","detail_info":"http://www.dhflpramericamf.com/downloads/sid-and-sai","ISIN":"INF223J01RC0","direct":"Y","switch_allowed":"N","stp_flag":"N","swp_flag":"N","sips":[{"sip_frequency":"MONTHLY","sip_dates":["1","2","3","4","5","6","7","8","9","10","11","12","13","14","15","16","17","18","19","20","21","22","23","24","25","26","27","28"],"sip_minimum_gap":"0","sip_maximum_gap":"60"},{"sip_frequency":"QUARTERLY","sip_dates":["1","2","3","4","5","6","7","8","9","10","11","12","13","14","15","16","17","18","19","20","21","22","23","24","25","26","27","28"],"sip_minimum_gap":"0","sip_maximum_gap":"60"}],"instant":"N","reinvestment":"Y","tags":[],"slug":"pgim-india-hybrid-debt-monthly-dividend-reinvest--PRAFD2-DR","channel_partner_code":"129AFD2","tax_period":1095,"nav":{"nav":10.9781,"date":"2019-07-28"},"last_nav":{"nav":10.9768,"date":"2019-07-27"},"jan_31_nav":10.4831,"volatility":3.34918,"returns":{"year_1":4.9347,"year_3":0.0,"year_5":0.0,"inception":5.6552,"date":"2019-07-26"},"start_date":"2017-04-17","face_value":10.0,"fund_type":"Hybrid","fund_category":"Conservative Hybrid Fund","plan":"DIVIDEND MONTHLY","expense_ratio":"0.71","expense_ratio_date":"2019-06-30","fund_manager":"Kumaresh Ramakrishnan; Alok Agarwal","crisil_rating":"Moderate","investment_objective":"The objective of Scheme is to seek to generate returns through investment primarily in Debt and Money Market Instruments and to generate capital appreciation by investing in equity and equity related instruments. However; there is no assurance that the investment objective of the Scheme will be realized and the Scheme does not assure or guarantee any returns.","portfolio_turnover":"1.11","maturity_type":"Open Ended","aum":180},{"code":"PRBPD2-DP","name":"PGIM India Banking \u0026 PSU Debt Monthly Dividend Payout Direct Plan","short_name":"PGIM India Banking \u0026 PSU Debt Monthly Dividend Payout","lump_available":"Y","sip_available":"Y","lump_min":5000.0,"lump_min_additional":1000.0,"lump_max":10000000000000.0,"lump_multiplier":1.0,"sip_min":500.0,"sip_max":999999999.0,"sip_multiplier":1.0,"sip_dates":["1","2","3","4","5","6","7","8","9","10","11","12","13","14","15","16","17","18","19","20","21","22","23","24","25","26","27","28"],"redemption_allowed":"Y","redemption_amount_multiple":1.0,"redemption_amount_minimum":100.0,"redemption_quantity_multiple":0.1,"redemption_quantity_minimum":0.1,"category":"Debt - Bonds","upsizecode_sip_dates":["1","2","3","4","5","6","7","8","9","10","11","12","13","14","15","16","17","18","19","20","21","22","23","24","25","26","27","28"],"sip_maximum_gap":60,"fund_house":"PGIMINDIAMUTUALFUND_MF","fund_name":"PGIM India Mutual Fund","short_code":"pgim","detail_info":"https://www.pgimindiamf.com/forms-and-updates/sid-and-sai","ISIN":"INF223J01SX4","direct":"Y","switch_allowed":"Y","stp_flag":"Y","swp_flag":"Y","sips":[{"sip_frequency":"MONTHLY","sip_dates":["1","2","3","4","5","6","7","8","9","10","11","12","13","14","15","16","17","18","19","20","21","22","23","24","25","26","27","28"],"sip_minimum_gap":"0","sip_maximum_gap":"60"},{"sip_frequency":"QUARTERLY","sip_dates":["1","2","3","4","5","6","7","8","9","10","11","12","13","14","15","16","17","18","19","20","21","22","23","24","25","26","27","28"],"sip_minimum_gap":"0","sip_maximum_gap":"60"}],"instant":"N","reinvestment":"N","tags":[],"slug":"pgim-india-banking-psu-debt-monthly-dividend-payout--PRBPD2-DP","channel_partner_code":"129BPD2","tax_period":1095,"nav":{"nav":10.7256,"date":"2020-03-12"},"last_nav":{"nav":10.8055,"date":"2020-03-11"},"jan_31_nav":10.3503,"volatility":2.55774,"returns":{"year_1":9.1309,"year_3":6.4235,"year_5":5.9051,"inception":6.5189,"date":"2020-03-12"},"start_date":"2013-02-22","face_value":10.0,"fund_type":"Debt","fund_category":"Banking and PSU Fund","plan":"DIVIDEND MONTHLY","expense_ratio":"0.1","expense_ratio_date":"2020-01-31","fund_manager":"Puneet Pal","crisil_rating":"Moderately Low","investment_objective":"The primary objective of the Scheme is to seek to generate income and capital appreciation by investing predominantly in debt instruments issued by banks; Public Sector Undertakings; Public Financial institutions and Municipal Bonds. However; there can be no assurance that the investment objective of the Scheme will be achieved. The Scheme does not guarantee/ indicate any returns.","portfolio_turnover":null,"maturity_type":"Open Ended","aum":580}]