[{"code":"TAIABZ-DP","name":"Tata Medium Term Dividend Payout Direct Plan","short_name":"Tata Medium Term Dividend Payout","lump_available":"Y","sip_available":"N","lump_min":5000.0,"lump_min_additional":1000.0,"lump_max":10000000000000.0,"lump_multiplier":1.0,"sip_min":0,"sip_max":0.0,"sip_multiplier":1,"sip_dates":[],"redemption_allowed":"Y","redemption_amount_multiple":1.0,"redemption_amount_minimum":500.0,"redemption_quantity_multiple":0.001,"redemption_quantity_minimum":50.0,"category":"Debt - Bonds","upsizecode_sip_dates":[],"sip_maximum_gap":30,"fund_house":"TATAMutualFund_MF","fund_name":"TATA Mutual Fund","short_code":"tata","detail_info":"https://www.tatamutualfund.com/downloads/scheme-information-document","ISIN":"INF277K01PH7","direct":"Y","switch_allowed":"Y","stp_flag":"Y","swp_flag":"Y","sips":[],"instant":"N","reinvestment":"N","tags":[],"slug":"tata-medium-term-dividend-payout--TAIABZ-DP","channel_partner_code":"TIABZ","tax_period":1095,"nav":{"nav":12.6955,"date":"2020-03-12"},"last_nav":{"nav":12.7519,"date":"2020-03-11"},"volatility":4.77874,"returns":{"year_1":6.1264,"year_3":5.769,"year_5":0.0,"inception":5.8595,"date":"2017-07-11"},"start_date":"2013-01-01","face_value":10.0,"fund_type":"Debt","fund_category":"Long Duration Fund","plan":"Bonus","expense_ratio":"0.91","expense_ratio_date":"2017-05-31","fund_manager":"Murthy Nagarajan","crisil_rating":"Moderate","investment_objective":"The investment objective of the scheme is to generate income and capital appreciation over a medium term.","portfolio_turnover":"0.13","maturity_type":"Open Ended","aum":960},{"code":"TAIABZ-DR","name":"Tata Medium Term Dividend Reinvest Direct Plan","short_name":"Tata Medium Term Dividend Reinvest","lump_available":"Y","sip_available":"Y","lump_min":5000.0,"lump_min_additional":1000.0,"lump_max":10000000000000.0,"lump_multiplier":1.0,"sip_min":500.0,"sip_max":999999999.0,"sip_multiplier":1.0,"sip_dates":["1","2","3","4","5","6","7","8","9","10","11","12","13","14","15","16","17","18","19","20","21","22","23","24","25","26","27","28","29","30"],"redemption_allowed":"Y","redemption_amount_multiple":1.0,"redemption_amount_minimum":500.0,"redemption_quantity_multiple":0.001,"redemption_quantity_minimum":50.0,"category":"Debt - Bonds","upsizecode_sip_dates":["1","2","3","4","5","6","7","8","9","10","11","12","13","14","15","16","17","18","19","20","21","22","23","24","25","26","27","28","29","30"],"sip_maximum_gap":90,"fund_house":"TATAMutualFund_MF","fund_name":"TATA Mutual Fund","short_code":"tata","detail_info":"https://www.tatamutualfund.com/downloads/scheme-information-document","ISIN":"INF277K01PH7","direct":"Y","switch_allowed":"Y","stp_flag":"Y","swp_flag":"Y","sips":[{"sip_frequency":"QUARTERLY","sip_dates":["1","2","3","4","5","6","7","8","9","10","11","12","13","14","15","16","17","18","19","20","21","22","23","24","25","26","27","28","29","30"],"sip_minimum_gap":"0","sip_maximum_gap":"90"},{"sip_frequency":"MONTHLY","sip_dates":["1","2","3","4","5","6","7","8","9","10","11","12","13","14","15","16","17","18","19","20","21","22","23","24","25","26","27","28","29","30"],"sip_minimum_gap":"0","sip_maximum_gap":"90"}],"instant":"N","reinvestment":"Y","tags":[],"slug":"tata-medium-term-dividend-reinvest--TAIABZ-DR","channel_partner_code":"TIABZ","tax_period":1095,"nav":{"nav":12.6955,"date":"2020-03-12"},"last_nav":{"nav":12.7519,"date":"2020-03-11"},"volatility":4.77874,"returns":{"year_1":6.1264,"year_3":5.769,"year_5":0.0,"inception":5.8595,"date":"2017-07-11"},"start_date":"2013-01-01","face_value":10.0,"fund_type":"Debt","fund_category":"Long Duration Fund","plan":"Bonus","expense_ratio":"0.91","expense_ratio_date":"2017-05-31","fund_manager":"Murthy Nagarajan","crisil_rating":"Moderate","investment_objective":"The investment objective of the scheme is to generate income and capital appreciation over a medium term.","portfolio_turnover":"0.13","maturity_type":"Open Ended","aum":960},{"code":"TAIAGZ-GR","name":"Tata Medium Term Growth Direct Plan","short_name":"Tata Medium Term","lump_available":"Y","sip_available":"Y","lump_min":5000.0,"lump_min_additional":1000.0,"lump_max":10000000000000.0,"lump_multiplier":1.0,"sip_min":500.0,"sip_max":999999999.0,"sip_multiplier":1.0,"sip_dates":["1","2","3","4","5","6","7","8","9","10","11","12","13","14","15","16","17","18","19","20","21","22","23","24","25","26","27","28","29","30"],"redemption_allowed":"Y","redemption_amount_multiple":1.0,"redemption_amount_minimum":500.0,"redemption_quantity_multiple":0.001,"redemption_quantity_minimum":50.0,"category":"Debt - Bonds","upsizecode_sip_dates":["1","2","3","4","5","6","7","8","9","10","11","12","13","14","15","16","17","18","19","20","21","22","23","24","25","26","27","28","29","30"],"sip_maximum_gap":90,"fund_house":"TATAMutualFund_MF","fund_name":"TATA Mutual Fund","short_code":"tata","detail_info":"https://www.tatamutualfund.com/downloads/scheme-information-document","ISIN":"INF277K01PI5","direct":"Y","switch_allowed":"Y","stp_flag":"Y","swp_flag":"Y","sips":[{"sip_frequency":"QUARTERLY","sip_dates":["1","2","3","4","5","6","7","8","9","10","11","12","13","14","15","16","17","18","19","20","21","22","23","24","25","26","27","28","29","30"],"sip_minimum_gap":"0","sip_maximum_gap":"90"},{"sip_frequency":"MONTHLY","sip_dates":["1","2","3","4","5","6","7","8","9","10","11","12","13","14","15","16","17","18","19","20","21","22","23","24","25","26","27","28","29","30"],"sip_minimum_gap":"0","sip_maximum_gap":"90"}],"instant":"N","reinvestment":"Z","tags":[],"slug":"tata-medium-term-growth--TAIAGZ-GR","channel_partner_code":"TIAGZ","tax_period":1095,"nav":{"nav":27.7236,"date":"2020-03-12"},"last_nav":{"nav":27.8469,"date":"2020-03-11"},"jan_31_nav":28.0331,"volatility":3.52857,"returns":{"year_1":-7.5386,"year_3":1.6161,"year_5":4.4263,"inception":6.1336,"date":"2020-03-12"},"start_date":"2013-01-01","face_value":10.0,"fund_type":"Debt","fund_category":"Medium Duration Fund","plan":"GROWTH","expense_ratio":"0.38","expense_ratio_date":"2020-01-31","fund_manager":"Murthy Nagarajan; Abhishek","crisil_rating":"Moderate","investment_objective":"The investment objective of the scheme is to generate income and capital appreciation over a medium term.","portfolio_turnover":"0.13","maturity_type":"Open Ended","aum":490},{"code":"TAINFDZ-DP","name":"Tata Infrastructure Dividend Payout Direct Plan","short_name":"Tata Infrastructure Dividend Payout","lump_available":"Y","sip_available":"N","lump_min":5000.0,"lump_min_additional":1000.0,"lump_max":10000000000000.0,"lump_multiplier":1.0,"sip_min":0,"sip_max":0.0,"sip_multiplier":1,"sip_dates":[],"redemption_allowed":"Y","redemption_amount_multiple":1.0,"redemption_amount_minimum":500.0,"redemption_quantity_multiple":0.001,"redemption_quantity_minimum":50.0,"category":"Equity","upsizecode_sip_dates":[],"sip_maximum_gap":30,"fund_house":"TATAMutualFund_MF","fund_name":"TATA Mutual Fund","short_code":"tata","detail_info":"https://www.tatamutualfund.com/downloads/scheme-information-document","ISIN":"INF277K01PP0","direct":"Y","switch_allowed":"Y","stp_flag":"Y","swp_flag":"Y","sips":[],"instant":"N","reinvestment":"N","tags":[],"slug":"tata-infrastructure-dividend-payout--TAINFDZ-DP","channel_partner_code":"TINFDZ","tax_period":365,"nav":{"nav":24.8047,"date":"2020-03-12"},"last_nav":{"nav":26.8556,"date":"2020-03-11"},"jan_31_nav":36.0751,"volatility":17.0446,"returns":{"year_1":-15.9639,"year_3":-1.4602,"year_5":0.6423,"inception":6.5726,"date":"2020-03-12"},"start_date":"2013-01-01","face_value":10.0,"fund_type":"Equity","fund_category":"Sectoral/Thematic","plan":"AS N WHEN","expense_ratio":"1.98","expense_ratio_date":"2020-01-31","fund_manager":"Abhinav Sharma; Rupesh Patel","crisil_rating":"High","investment_objective":"To provide income distribution and or medium to long term capital gains by investing predominantly in equity; equity related instrument of companies in infrastructure sector.","portfolio_turnover":"0.2286","maturity_type":"Open Ended","aum":4690},{"code":"TAINFDZ-DR","name":"Tata Infrastructure Dividend Reinvest Direct Plan","short_name":"Tata Infrastructure Dividend Reinvest","lump_available":"Y","sip_available":"Y","lump_min":5000.0,"lump_min_additional":1000.0,"lump_max":10000000000000.0,"lump_multiplier":1.0,"sip_min":500.0,"sip_max":999999999.0,"sip_multiplier":1.0,"sip_dates":["1","2","3","4","5","6","7","8","9","10","11","12","13","14","15","16","17","18","19","20","21","22","23","24","25","26","27","28","29","30"],"redemption_allowed":"Y","redemption_amount_multiple":1.0,"redemption_amount_minimum":500.0,"redemption_quantity_multiple":0.001,"redemption_quantity_minimum":50.0,"category":"Equity","upsizecode_sip_dates":["1","2","3","4","5","6","7","8","9","10","11","12","13","14","15","16","17","18","19","20","21","22","23","24","25","26","27","28","29","30"],"sip_maximum_gap":90,"fund_house":"TATAMutualFund_MF","fund_name":"TATA Mutual Fund","short_code":"tata","detail_info":"https://www.tatamutualfund.com/downloads/scheme-information-document","ISIN":"INF277K01PP0","direct":"Y","switch_allowed":"Y","stp_flag":"Y","swp_flag":"Y","sips":[{"sip_frequency":"MONTHLY","sip_dates":["1","2","3","4","5","6","7","8","9","10","11","12","13","14","15","16","17","18","19","20","21","22","23","24","25","26","27","28","29","30"],"sip_minimum_gap":"0","sip_maximum_gap":"90"},{"sip_frequency":"QUARTERLY","sip_dates":["1","2","3","4","5","6","7","8","9","10","11","12","13","14","15","16","17","18","19","20","21","22","23","24","25","26","27","28","29","30"],"sip_minimum_gap":"0","sip_maximum_gap":"90"}],"instant":"N","reinvestment":"Y","tags":[],"slug":"tata-infrastructure-dividend-reinvest--TAINFDZ-DR","channel_partner_code":"TINFDZ","tax_period":365,"nav":{"nav":24.8047,"date":"2020-03-12"},"last_nav":{"nav":26.8556,"date":"2020-03-11"},"jan_31_nav":36.0751,"volatility":17.0446,"returns":{"year_1":-15.9639,"year_3":-1.4602,"year_5":0.6423,"inception":6.5726,"date":"2020-03-12"},"start_date":"2013-01-01","face_value":10.0,"fund_type":"Equity","fund_category":"Sectoral/Thematic","plan":"AS N WHEN","expense_ratio":"1.98","expense_ratio_date":"2020-01-31","fund_manager":"Abhinav Sharma; Rupesh Patel","crisil_rating":"High","investment_objective":"To provide income distribution and or medium to long term capital gains by investing predominantly in equity; equity related instrument of companies in infrastructure sector.","portfolio_turnover":"0.2286","maturity_type":"Open Ended","aum":4690},{"code":"TAINFGZ-GR","name":"Tata Infrastructure Growth Direct Plan","short_name":"Tata Infrastructure","lump_available":"Y","sip_available":"Y","lump_min":5000.0,"lump_min_additional":1000.0,"lump_max":10000000000000.0,"lump_multiplier":1.0,"sip_min":500.0,"sip_max":999999999.0,"sip_multiplier":1.0,"sip_dates":["1","2","3","4","5","6","7","8","9","10","11","12","13","14","15","16","17","18","19","20","21","22","23","24","25","26","27","28","29","30"],"redemption_allowed":"Y","redemption_amount_multiple":1.0,"redemption_amount_minimum":500.0,"redemption_quantity_multiple":0.001,"redemption_quantity_minimum":50.0,"category":"Equity","upsizecode_sip_dates":["1","2","3","4","5","6","7","8","9","10","11","12","13","14","15","16","17","18","19","20","21","22","23","24","25","26","27","28","29","30"],"sip_maximum_gap":90,"fund_house":"TATAMutualFund_MF","fund_name":"TATA Mutual Fund","short_code":"tata","detail_info":"https://www.tatamutualfund.com/downloads/scheme-information-document","ISIN":"INF277K01PQ8","direct":"Y","switch_allowed":"Y","stp_flag":"Y","swp_flag":"Y","sips":[{"sip_frequency":"MONTHLY","sip_dates":["1","2","3","4","5","6","7","8","9","10","11","12","13","14","15","16","17","18","19","20","21","22","23","24","25","26","27","28","29","30"],"sip_minimum_gap":"0","sip_maximum_gap":"90"},{"sip_frequency":"QUARTERLY","sip_dates":["1","2","3","4","5","6","7","8","9","10","11","12","13","14","15","16","17","18","19","20","21","22","23","24","25","26","27","28","29","30"],"sip_minimum_gap":"0","sip_maximum_gap":"90"}],"instant":"N","reinvestment":"Z","tags":[],"slug":"tata-infrastructure-growth--TAINFGZ-GR","channel_partner_code":"TINFGZ","tax_period":365,"nav":{"nav":47.3705,"date":"2020-03-12"},"last_nav":{"nav":51.2877,"date":"2020-03-11"},"jan_31_nav":64.0361,"volatility":16.4528,"returns":{"year_1":-15.9847,"year_3":-1.5455,"year_5":0.6079,"inception":6.5487,"date":"2020-03-12"},"start_date":"2013-01-01","face_value":10.0,"fund_type":"Equity","fund_category":"Sectoral/Thematic","plan":"GROWTH","expense_ratio":"1.98","expense_ratio_date":"2020-01-31","fund_manager":"Abhinav Sharma; Rupesh Patel","crisil_rating":"High","investment_objective":"To provide income distribution and or medium to long term capital gains by investing predominantly in equity; equity related instrument of companies in infrastructure sector.","portfolio_turnover":"0.2286","maturity_type":"Open Ended","aum":4690},{"code":"TALSGZ-GR","name":"Tata Money Market Growth Direct Plan","short_name":"Tata Money Market","lump_available":"Y","sip_available":"Y","lump_min":5000.0,"lump_min_additional":1000.0,"lump_max":10000000000000.0,"lump_multiplier":1.0,"sip_min":500.0,"sip_max":999999999.0,"sip_multiplier":1.0,"sip_dates":["1","2","3","4","5","6","7","8","9","10","11","12","13","14","15","16","17","18","19","20","21","22","23","24","25","26","27","28","29","30"],"redemption_allowed":"Y","redemption_amount_multiple":1.0,"redemption_amount_minimum":1000.0,"redemption_quantity_multiple":0.001,"redemption_quantity_minimum":1.0,"category":"Debt - Bonds","upsizecode_sip_dates":["1","2","3","4","5","6","7","8","9","10","11","12","13","14","15","16","17","18","19","20","21","22","23","24","25","26","27","28","29","30"],"sip_maximum_gap":90,"fund_house":"TATAMutualFund_MF","fund_name":"TATA Mutual Fund","short_code":"tata","detail_info":"https://www.tatamutualfund.com/downloads/scheme-information-document","ISIN":"INF277K01PR6","direct":"Y","switch_allowed":"Y","stp_flag":"Y","swp_flag":"Y","sips":[{"sip_frequency":"MONTHLY","sip_dates":["1","2","3","4","5","6","7","8","9","10","11","12","13","14","15","16","17","18","19","20","21","22","23","24","25","26","27","28","29","30"],"sip_minimum_gap":"0","sip_maximum_gap":"90"},{"sip_frequency":"QUARTERLY","sip_dates":["1","2","3","4","5","6","7","8","9","10","11","12","13","14","15","16","17","18","19","20","21","22","23","24","25","26","27","28","29","30"],"sip_minimum_gap":"0","sip_maximum_gap":"90"}],"instant":"N","reinvestment":"Z","tags":[],"slug":"tata-money-market-growth--TALSGZ-GR","channel_partner_code":"TLSGZ","tax_period":1095,"nav":{"nav":3450.04,"date":"2020-03-12"},"last_nav":{"nav":3451.8,"date":"2020-03-11"},"jan_31_nav":3166.41,"volatility":0.300707,"returns":{"year_1":7.5573,"year_3":4.8968,"year_5":6.0536,"inception":6.9913,"date":"2020-03-12"},"start_date":"2013-01-01","face_value":1000.0,"fund_type":"Debt","fund_category":"Money Market Fund","plan":"GROWTH","expense_ratio":"0.22","expense_ratio_date":"2020-01-31","fund_manager":"Amit Somani","crisil_rating":"Low","investment_objective":"The investment objective is to generate returns with reasonable liquidity to the unitholders by investing in money market instruments.","portfolio_turnover":null,"maturity_type":"Open Ended","aum":6510},{"code":"TAGRODZ-DP","name":"Tata Mid Cap Growth Fund Dividend Payout Direct Plan","short_name":"Tata Mid Cap Growth Fund Dividend Payout","lump_available":"Y","sip_available":"N","lump_min":5000.0,"lump_min_additional":1000.0,"lump_max":10000000000000.0,"lump_multiplier":1.0,"sip_min":0,"sip_max":0.0,"sip_multiplier":1,"sip_dates":[],"redemption_allowed":"Y","redemption_amount_multiple":1.0,"redemption_amount_minimum":500.0,"redemption_quantity_multiple":0.001,"redemption_quantity_minimum":50.0,"category":"Equity","upsizecode_sip_dates":[],"sip_maximum_gap":30,"fund_house":"TATAMutualFund_MF","fund_name":"TATA Mutual Fund","short_code":"tata","detail_info":"https://www.tatamutualfund.com/downloads/scheme-information-document","ISIN":"INF277K01PX4","direct":"Y","switch_allowed":"Y","stp_flag":"Y","swp_flag":"Y","sips":[],"instant":"N","reinvestment":"N","tags":[],"slug":"tata-mid-cap-growth-fund-dividend-payout--TAGRODZ-DP","channel_partner_code":"TGRODZ","tax_period":365,"nav":{"nav":45.1522,"date":"2020-03-12"},"last_nav":{"nav":48.5435,"date":"2020-03-11"},"jan_31_nav":53.4848,"volatility":15.3802,"returns":{"year_1":-5.7437,"year_3":4.752,"year_5":4.8907,"inception":15.0122,"date":"2020-03-12"},"start_date":"2013-01-01","face_value":10.0,"fund_type":"Equity","fund_category":"Mid Cap Fund","plan":"AS N WHEN","expense_ratio":"1.3","expense_ratio_date":"2020-01-31","fund_manager":"Rupesh Patel; Ennettee Fernandes","crisil_rating":"Moderately High","investment_objective":"To provide income distribution and or medium to long term capital gains. The scheme will make investments in equity and equity related instruments of well researched growth oriented companies.","portfolio_turnover":"0.2715","maturity_type":"Open Ended","aum":8370},{"code":"TAGRODZ-DR","name":"Tata Mid Cap Growth Fund Dividend Reinvest Direct Plan","short_name":"Tata Mid Cap Growth Fund Dividend Reinvest","lump_available":"Y","sip_available":"Y","lump_min":5000.0,"lump_min_additional":1000.0,"lump_max":10000000000000.0,"lump_multiplier":1.0,"sip_min":500.0,"sip_max":999999999.0,"sip_multiplier":1.0,"sip_dates":["1","2","3","4","5","6","7","8","9","10","11","12","13","14","15","16","17","18","19","20","21","22","23","24","25","26","27","28","29","30"],"redemption_allowed":"Y","redemption_amount_multiple":1.0,"redemption_amount_minimum":500.0,"redemption_quantity_multiple":0.001,"redemption_quantity_minimum":50.0,"category":"Equity","upsizecode_sip_dates":["1","2","3","4","5","6","7","8","9","10","11","12","13","14","15","16","17","18","19","20","21","22","23","24","25","26","27","28","29","30"],"sip_maximum_gap":90,"fund_house":"TATAMutualFund_MF","fund_name":"TATA Mutual Fund","short_code":"tata","detail_info":"https://www.tatamutualfund.com/downloads/scheme-information-document","ISIN":"INF277K01PX4","direct":"Y","switch_allowed":"Y","stp_flag":"Y","swp_flag":"Y","sips":[{"sip_frequency":"QUARTERLY","sip_dates":["1","2","3","4","5","6","7","8","9","10","11","12","13","14","15","16","17","18","19","20","21","22","23","24","25","26","27","28","29","30"],"sip_minimum_gap":"0","sip_maximum_gap":"90"},{"sip_frequency":"MONTHLY","sip_dates":["1","2","3","4","5","6","7","8","9","10","11","12","13","14","15","16","17","18","19","20","21","22","23","24","25","26","27","28","29","30"],"sip_minimum_gap":"0","sip_maximum_gap":"90"}],"instant":"N","reinvestment":"Y","tags":[],"slug":"tata-mid-cap-growth-fund-dividend-reinvest--TAGRODZ-DR","channel_partner_code":"TGRODZ","tax_period":365,"nav":{"nav":45.1522,"date":"2020-03-12"},"last_nav":{"nav":48.5435,"date":"2020-03-11"},"jan_31_nav":53.4848,"volatility":15.3802,"returns":{"year_1":-5.7437,"year_3":4.752,"year_5":4.8907,"inception":15.0122,"date":"2020-03-12"},"start_date":"2013-01-01","face_value":10.0,"fund_type":"Equity","fund_category":"Mid Cap Fund","plan":"AS N WHEN","expense_ratio":"1.3","expense_ratio_date":"2020-01-31","fund_manager":"Rupesh Patel; Ennettee Fernandes","crisil_rating":"Moderately High","investment_objective":"To provide income distribution and or medium to long term capital gains. The scheme will make investments in equity and equity related instruments of well researched growth oriented companies.","portfolio_turnover":"0.2715","maturity_type":"Open Ended","aum":8370},{"code":"TAGROGZ-GR","name":"Tata Mid Cap Growth Fund Growth Direct Plan","short_name":"Tata Mid Cap Growth Fund","lump_available":"Y","sip_available":"Y","lump_min":5000.0,"lump_min_additional":1000.0,"lump_max":10000000000000.0,"lump_multiplier":1.0,"sip_min":500.0,"sip_max":999999999.0,"sip_multiplier":1.0,"sip_dates":["1","2","3","4","5","6","7","8","9","10","11","12","13","14","15","16","17","18","19","20","21","22","23","24","25","26","27","28","29","30"],"redemption_allowed":"Y","redemption_amount_multiple":1.0,"redemption_amount_minimum":500.0,"redemption_quantity_multiple":0.001,"redemption_quantity_minimum":50.0,"category":"Equity","upsizecode_sip_dates":["1","2","3","4","5","6","7","8","9","10","11","12","13","14","15","16","17","18","19","20","21","22","23","24","25","26","27","28","29","30"],"sip_maximum_gap":90,"fund_house":"TATAMutualFund_MF","fund_name":"TATA Mutual Fund","short_code":"tata","detail_info":"https://www.tatamutualfund.com/downloads/scheme-information-document","ISIN":"INF277K01PY2","direct":"Y","switch_allowed":"Y","stp_flag":"Y","swp_flag":"Y","sips":[{"sip_frequency":"MONTHLY","sip_dates":["1","2","3","4","5","6","7","8","9","10","11","12","13","14","15","16","17","18","19","20","21","22","23","24","25","26","27","28","29","30"],"sip_minimum_gap":"0","sip_maximum_gap":"90"},{"sip_frequency":"QUARTERLY","sip_dates":["1","2","3","4","5","6","7","8","9","10","11","12","13","14","15","16","17","18","19","20","21","22","23","24","25","26","27","28","29","30"],"sip_minimum_gap":"0","sip_maximum_gap":"90"}],"instant":"N","reinvestment":"Z","tags":[],"slug":"tata-mid-cap-growth-fund-growth--TAGROGZ-GR","channel_partner_code":"TGROGZ","tax_period":365,"nav":{"nav":136.579,"date":"2020-03-12"},"last_nav":{"nav":146.837,"date":"2020-03-11"},"jan_31_nav":150.942,"volatility":14.9251,"returns":{"year_1":-5.7219,"year_3":5.0412,"year_5":5.0713,"inception":15.1478,"date":"2020-03-12"},"start_date":"2013-01-01","face_value":10.0,"fund_type":"Equity","fund_category":"Mid Cap Fund","plan":"GROWTH","expense_ratio":"1.3","expense_ratio_date":"2020-01-31","fund_manager":"Rupesh Patel; Ennettee Fernandes","crisil_rating":"Moderately High","investment_objective":"To provide income distribution and or medium to long term capital gains. The scheme will make investments in equity and equity related instruments of well researched growth oriented companies.","portfolio_turnover":"0.2715","maturity_type":"Open Ended","aum":8370}]